{"data":[{"url":"/artist/Blue_Dxxk_%EB%B8%94%EB%A3%A8%EB%8D%95/Beautiful_Day/","subject":"Beautiful Day","artist":"Blue Dxxk (블루덕)","lyric":"Good Morning \n 햇살의 끝에 니가 서있어\n 눈 떴다 감았다 다시 떠봐도\n 믿기 힘든걸\n 반듯이 놓여진 접시 위치까지도\n 돌렸다 들었다 다시 놔도\n 고민되는걸\n 상상했던 "},{"url":"/artist/Blue_Dxxk_%EB%B8%94%EB%A3%A8%EB%8D%95/%EB%A7%A4%EC%9D%BC%EB%B4%90_Day_by_Day/","subject":"매일봐 (Day by Day)","artist":"Blue Dxxk (블루덕)","lyric":"Girl I'm with you girl\n 하지만 자꾸 너와 \n 눈이 마주칠 때면\n 고갤 돌려 \n 긴장한 내 모습 볼까 봐\n 가끔은 이런 내가 나도 \n 어색하기만 하죠\n 내 얘기 "}]}