{"data":[{"url":"/artist/Ella_Fitzgerald/Dont_Fence_Me_In/","subject":"Don`t Fence Me In","artist":"Ella Fitzgerald","lyric":"Wildcat Kelley, lookin' mighty pale\n Was standin' by the sherrif's side\n And when the sherrif said I"},{"url":"/artist/Ella_Fitzgerald/I_Concentrate_On_You/","subject":"I Concentrate On You","artist":"Ella Fitzgerald","lyric":"Whenever skies look gray to me\n And trouble begins to brew\n Whenever the winter winds become too str"},{"url":"/artist/Ella_Fitzgerald/Ive_Got_You_Under_My_Skin/","subject":"I`ve Got You Under My Skin","artist":"Ella Fitzgerald","lyric":"I've got you under my skin\n I've got you deep in the heart of me\n So deep in my heart that you're re"},{"url":"/artist/Ella_Fitzgerald/So_In_Love/","subject":"So In Love","artist":"Ella Fitzgerald","lyric":"Strange dear, but true dear\n When I'm close to you, dear\n The stars fill the sky\n So in love with yo"},{"url":"/artist/Ella_Fitzgerald/Ace_In_The_Hole/","subject":"Ace In The Hole","artist":"Ella Fitzgerald","lyric":"Sad times, may follow your tracks\n Bad times, may bar you from Sak's\n At times, when Satan in slacks"},{"url":"/artist/Ella_Fitzgerald/Night_And_Day/","subject":"Night And Day","artist":"Ella Fitzgerald","lyric":"Like the beat beat beat of the tom tom\n When the jungle shadows fall\n Like the tick tick tock of the"},{"url":"/artist/Ella_Fitzgerald/Its_DeLovely/","subject":"It`s DeLovely","artist":"Ella Fitzgerald","lyric":"I feel a sudden urge to sing the kind of ditty that invokes the Spring\n So, control your desire to c"},{"url":"/artist/Ella_Fitzgerald/Love_For_Sale/","subject":"Love For Sale","artist":"Ella Fitzgerald","lyric":"When the only sound in the empty street\n Is the heavy tread of the heavy feet\n That belong to a lone"},{"url":"/artist/Ella_Fitzgerald/Youre_The_Top/","subject":"You`re The Top","artist":"Ella Fitzgerald","lyric":"At words poetic I'm so pathetic\n That I always have found it best\n Instead of getting 'em off my che"},{"url":"/artist/Ella_Fitzgerald/What_Is_This_Thing_Called_Love_/","subject":"What Is This Thing Called Love?","artist":"Ella Fitzgerald","lyric":"What is this thing called love\n This funny thing called love\n Just who can solve its mystery\n Why sh"}]}