{"last":1,"data":[{"url":"/artist/%EB%84%A4%EB%8D%9C%EB%9E%80%EB%93%9C_%ED%8A%A4%EB%A6%BD%EB%86%8D%EC%9E%A5/%EB%B9%84_%EC%98%A4%EB%8A%94_%EB%82%A0_%EB%B2%9A%EA%BD%83%EC%B2%98%EB%9F%BC_%EB%84%88%EB%8F%84_%EC%96%B4%EB%8A%90_%EC%88%9C%EA%B0%84_%EC%82%AC%EB%9D%BC%EC%A0%B8_%EB%B2%84%EB%A0%B8%EC%96%B4/","subject":"비 오는 날 벚꽃처럼 너도 어느 순간 사라져 버렸어","artist":"네덜란드 튤립농장","lyric":"비 오는 날 벚꽃은\n 바닥에 떨어졌지만\n 내일이면 거린 하얗게 물들 거야\n 널 향한 내 마음도\n 바닥에 떨어졌지만\n 내일이면 난 또 다른 사람을 쳐다봐\n 너를 만나면 후회할 것 같"},{"url":"/artist/%EB%84%A4%EB%8D%9C%EB%9E%80%EB%93%9C_%ED%8A%A4%EB%A6%BD%EB%86%8D%EC%9E%A5/%ED%8A%A4%EB%A6%BD_%EC%97%90%EC%84%B8%EC%9D%B4_%EB%B9%84%EB%B2%9A%EB%84%88/","subject":"튤립 에세이 (비벚너)","artist":"네덜란드 튤립농장","lyric":"지하철이 덜컹거리는 소리와 함께 손전화가 불규칙하게 울려댔다. 서로 바쁘다며 조별 과제 모임을 조금만 미루자는 내용이었다. 속이 시커먼 사람들이 문장 끝에 의무감으로 늘어놓는 키읔"},{"url":"/artist/%EB%84%A4%EB%8D%9C%EB%9E%80%EB%93%9C_%ED%8A%A4%EB%A6%BD%EB%86%8D%EC%9E%A5/%ED%8A%A4%EB%A6%BD_%EC%97%90%EC%84%B8%EC%9D%B4_%EC%A2%8B%EC%95%84%ED%95%98%EB%A9%B4_%EC%95%8C%EA%B2%8C%EB%8F%BC%EC%9A%94/","subject":"튤립 에세이 (좋아하면 알게돼요)","artist":"네덜란드 튤립농장","lyric":"정신없이 어두운 카페, 낮은 테이블, 자리가 부족하니 불편하더라도 합석을 해줬으면 한다는 카페 주인의 말, 그리고 내 오른쪽 자리에 당신이 앉아 있었다. 어색한 공기 속에 실없는 "},{"url":"/artist/%EB%84%A4%EB%8D%9C%EB%9E%80%EB%93%9C_%ED%8A%A4%EB%A6%BD%EB%86%8D%EC%9E%A5/%EC%A2%8B%EC%95%84%ED%95%98%EB%A9%B4_%EC%95%8C%EA%B2%8C%EB%8F%BC%EC%9A%94/","subject":"좋아하면 알게돼요","artist":"네덜란드 튤립농장","lyric":"좋아하면 알게 돼요\n 내가 왜 그런 말을 했는지 \n 지금 무슨 생각을 하는지\n 나를 좋아하면 알게 돼요\n 그대 지금 어디에 있는지\n 나를 어떻게 생각하는지 \n 아주 사소한 것 하나"}]}