{"data":[{"url":"/artist/%EB%B0%95%EA%B7%80%EC%9E%90/%EC%82%AC%EB%9E%91%EC%9D%98_%ED%95%AD%EA%B5%AC/","subject":"사랑의 항구","artist":"박귀자","lyric":"항구 항구 여기는 항구 \n 가슴이 시원하구나\n 사투리는 서로가 달라도 \n 마음이 통하는구나\n 배 닿는 부두마다 사랑이더라\n 배 떠난 부두마다 눈물이더라\n 아아 아아 아 여기는 항구"},{"url":"/artist/%EB%B0%95%EA%B7%80%EC%9E%90/%EB%96%A0%EB%82%98%EB%B2%84%EB%A6%B0_%EA%B7%B8%EC%82%AC%EB%9E%8C/","subject":"떠나버린 그사람","artist":"박귀자","lyric":"하늘같이 믿었더니 \n 목숨 바쳐 믿었더니 \n 마음을 주고 사랑을 주고 \n 떠나버린 그 사람 \n 첫사랑 정 때문에 \n 떠나지도 못하고 \n 눈물로 세월 가네 \n 돌아올 줄 모르네 \n "}]}