{"data":[{"url":"/artist/%EB%B0%9C%EB%9D%BC%EB%93%9C_%EA%B3%B5%EC%9E%A5/%EC%97%AC%ED%96%89%EC%9D%84_%EB%96%A0%EB%82%98%EC%9A%94/","subject":"여행을 떠나요","artist":"발라드 공장","lyric":"푸른 언덕에 배낭을 메고\n 황금빛 태양 축제를 여는\n 광야를 향해서 계곡을 향해서\n 먼동이 트는 이른아침에\n 도시의 소음 수많은 사람\n 빌딩 숲속을 벗어나봐요\n 메아리 소리가 들려"},{"url":"/artist/%EB%B0%9C%EB%9D%BC%EB%93%9C_%EA%B3%B5%EC%9E%A5/%EC%82%AC%EB%9E%91%EC%9D%B4_%EB%8B%A4_%EA%B7%B8%EB%9F%B0_%EA%B1%B0%EB%8B%88%EA%B9%8C/","subject":"사랑이 다 그런 거니까","artist":"발라드 공장","lyric":"아침해가 비틀거리면 \n 수줍은듯 달빛뒤로 몸을 숨기면 \n 그달빛은 나를 만지며\n 내 가슴에 비를 내리네\n \n 바보같은 사랑을 했었어 바보같은 이별을 했어\n 죽을만큼 널 사랑했는데 "},{"url":"/artist/%EB%B0%9C%EB%9D%BC%EB%93%9C_%EA%B3%B5%EC%9E%A5/%EB%A8%BC_%ED%9B%97%EB%82%A0/","subject":"먼 훗날","artist":"발라드 공장","lyric":"널 이젠 잊겠어 내 깊은 그리움으로 \n 이 밤을 지새운 건 아니였는데\n 이제는 닦아낼 눈물이 없어\n \n 하고픈 말 서럽게 쌓여만 가고\n \n 기억되는 그리움의 아픔이 너무 두려워\n "},{"url":"/artist/%EB%B0%9C%EB%9D%BC%EB%93%9C_%EA%B3%B5%EC%9E%A5/2_Different_Tears/","subject":"2 Different Tears","artist":"발라드 공장","lyric":"Gave me 2 different tears 너 때문에 난 \n 기뻐서 울었고 슬퍼서 울었어 So I hate you \n So I love you, So I hate you, So"},{"url":"/artist/%EB%B0%9C%EB%9D%BC%EB%93%9C_%EA%B3%B5%EC%9E%A5/%EB%B3%84/","subject":"별","artist":"발라드 공장","lyric":"아무말 없이 이별을 준비 했나요\n 그대 마음 지금쯤 얼마나 아플지 눈물이 흘러요\n 힘들었나요 나와 함께 했던 날이 \n 내 모든걸 버려요\n 미련한 마음에 그대를 알지 못한 나에요\n "},{"url":"/artist/%EB%B0%9C%EB%9D%BC%EB%93%9C_%EA%B3%B5%EC%9E%A5/%EC%9E%8A%EC%97%88%EB%8B%88/","subject":"잊었니","artist":"발라드 공장","lyric":"진실은 거짓이 되고 술은 눈물과 섞여\n 쓰라린 내 맘 속을 태워 내려가네 여전히\n 니 품 안에 웃던 그 날\n 그 날에 멈춰 미소 져 보는 난\n 내일이 되면 꿈이라고\n \n 오늘도 애"},{"url":"/artist/%EB%B0%9C%EB%9D%BC%EB%93%9C_%EA%B3%B5%EC%9E%A5/%EC%9C%BC%EB%9D%BC%EC%B0%A8%EC%B0%A8/","subject":"으라차차","artist":"발라드 공장","lyric":"다시 내게 찾아온거야 너무 빨리 돌아온거야\n 네 모습을 보여봐 쑥스러워 그런거야\n 빗소리를 듣고 온거야 밤이 너를 다시 불러낸거야\n 너를 밀어내려고 이렇게 난 소리질러\n \n 으라차"},{"url":"/artist/%EB%B0%9C%EB%9D%BC%EB%93%9C_%EA%B3%B5%EC%9E%A5/%EC%9D%BC%EA%B8%B0/","subject":"일기","artist":"발라드 공장","lyric":"12월 9일 목요일 사랑하는 사람과 \n 마지막 하루를 보냈다고 \n 4월에 나눌 인사를 미리 서둘러 하고 \n 세상과도 이별한다고 \n \n 눈을 감으면 깨어나지 못하면 \n 매일 써오던 "},{"url":"/artist/%EB%B0%9C%EB%9D%BC%EB%93%9C_%EA%B3%B5%EC%9E%A5/%EB%82%B4_%EC%82%AC%EB%9E%8C/","subject":"내 사람","artist":"발라드 공장","lyric":"내 가슴속에 사는 사람 내가 그토록 아끼는 사람 \n 너무 소중해 마음껏 안아보지도 못했던 \n 누구에게나 흔한 행복 한 번도 준적이 없어서 \n 맘 놓고 웃어본 적도 없는 그댈 사랑합"},{"url":"/artist/%EB%B0%9C%EB%9D%BC%EB%93%9C_%EA%B3%B5%EC%9E%A5/%EC%86%90%ED%86%B1%EC%9D%B4_%EB%B9%A0%EC%A0%B8%EC%84%9C/","subject":"손톱이 빠져서","artist":"발라드 공장","lyric":"생각나니 읽어봤니 우리 마지막 편지\n 구겨버렸지 찢어버렸지 넌 그런 사람이니까\n 손톱이 다 빠지도록 꼭꼭 눌러 쓴 그 결심은 \n 나의 마음 속에 여기 어딘가에 여태 박혀져 있는데 "}]}