{"data":[{"url":"/artist/%EB%A1%9C%EC%BC%93%ED%8A%B8_%EC%95%84%EA%B0%80%EC%94%A8/%ED%9D%B0%EB%A8%B8%EB%A6%AC/","subject":"흰머리","artist":"로켓트 아가씨","lyric":"오늘 우연히 발견한\n 흰머리를 바라보니\n 나도 이제 늙었구나 꺽였구나\n 어릴 적 용돈 벌이로\n 뽑아 드렸던 흰머리\n 내가 이제 그 나이가 되었구나\n 아무것도 이룬 게 없는데\n 시간"},{"url":"/artist/%EB%A1%9C%EC%BC%93%ED%8A%B8_%EC%95%84%EA%B0%80%EC%94%A8/%EB%A9%88%EC%B6%B0%EB%B2%84%EB%A6%B0_%EC%8B%9C%EA%B0%84/","subject":"멈춰버린 시간","artist":"로켓트 아가씨","lyric":"어쩌면 이렇게 달라져 버린 걸까\n 너와 나 이토록 멀어져 버린 걸까\n 헝클어진 감정에 발이 묶여\n 다가가려 해 봐도\n 한번도 맘 놓고 웃어본 적이 없어\n 내 마음 깊은 곳 들어온 "},{"url":"/artist/%EB%A1%9C%EC%BC%93%ED%8A%B8_%EC%95%84%EA%B0%80%EC%94%A8/%EA%B7%B8%EB%8C%80_%EC%9D%B4%EC%A0%9C_%EC%95%88%EB%85%95/","subject":"그대 이제 안녕","artist":"로켓트 아가씨","lyric":"나 다 알아요\n 설명하지 않아도 변명하지 않아도\n 나 다 이해해요\n 그럴 수밖에 없는 상황이라는 것을\n 먼저 말해요\n 차마 하기 힘든 말\n 절대 하지 말잔 말\n 내가 할까요\n 그대"},{"url":"/artist/love/7%E6%9C%88%EC%9D%98%EC%86%8C%EB%82%98%ED%83%80/","subject":"7月의소나타","artist":"love","lyric":"사랑했으면 오 그리워해요\n 그리워해요 오 그리워해요\n 사랑했으면 그러면 안돼요\n 돌아선 니 모습을 그리워해요\n 사랑한다는 그말이 우스워졌나\n 웃으며 보낸다는 말이 우스워 정말\n 사"},{"url":"/artist/love/%EC%98%A4%ED%94%88%EC%B9%B4_%EC%95%88%EC%97%90%EC%84%9C/","subject":"오픈카 안에서","artist":"love","lyric":"너와 내가 만났었던 오픈카 안에서\n 너와 내가 마셨었던 캔맥주 두 캔 Uh\n 불금이면 항상 그곳 이태원\n Party Uh huh\n 나를 보며 사랑한다는 그 말\n huh 그녀한테 해"},{"url":"/artist/%EC%8B%A0%EC%9E%90%EC%9B%90/%EC%82%AC%EB%9E%91%EC%9D%B4%EB%9D%BC%EB%A9%B4/","subject":"사랑이라면","artist":"신자원","lyric":"사랑이라면\n 사랑이라면\n 그럴 수가 있나요\n 사랑이라면\n 사랑이라면\n 미워할 순 없잖아요\n 가끔은\n 사랑의 아픔도\n 필요하겠지만은\n 어쩌면 당신은\n 그렇게 많은\n 상처만을 주나요\n"},{"url":"/artist/%EC%8B%A0%EC%9E%90%EC%9B%90/%EC%82%AC%EB%9E%91%EC%9D%80_%EB%98%90%EB%8B%A4%EB%A5%B8_%EB%A7%8C%EB%82%A8%EC%9D%B4_%EB%90%98%EC%96%B4/","subject":"사랑은 또다른 만남이 되어","artist":"신자원","lyric":"밤비에 젖어가는 \n 거리 끝자리 \n 카페에 들어서면은 \n 우리가 만났었던 \n 지난 시절이 \n 기억을 스쳐 지나네 \n 가슴을 파고드는 \n 외로움으로 \n 찻잔을 기울이면은 \n 진하게 "},{"url":"/artist/%EC%8B%A0%EC%9E%90%EC%9B%90/%EA%B7%B8%EB%9F%B0%EA%B1%B0%EB%9D%BC%EC%A7%80/","subject":"그런거라지","artist":"신자원","lyric":"그런 거라지\n 그런 거라지\n 사랑은 그런 거라지\n 사랑했던 마음만큼\n 미움이 생겨난다지\n 그런 거라지 이별은\n 아마도 그런 거라지\n 그리워한 마음만큼\n 그 마음 아픈 거라지\n 사랑"},{"url":"/artist/%EC%8B%A0%EC%9E%90%EC%9B%90/%EB%B0%98%EC%A7%80%EB%91%90%EA%B3%A0_%EA%B0%91%EB%8B%88%EB%8B%A4/","subject":"반지두고 갑니다","artist":"신자원","lyric":"어떻게 시작해야 하나\n 어떻게 말을 해야 하나\n 영원을 맹세해놓고\n 순간을 기억해야 해\n 똑같은 말을 해도\n 당신의 말이\n 더욱 뚜렷이 남는 건\n 당신의 얼굴로 가득한\n 내 가슴의"},{"url":"/artist/%EC%8B%A0%EC%9E%90%EC%9B%90/%EA%B7%B8%EB%95%8C%EB%8A%94_%EB%82%98%EC%9D%98_%EB%8B%B9%EC%8B%A0%EC%9D%B4_%EC%95%84%EB%8B%88%EC%97%88%EC%96%B4%EC%9A%94/","subject":"그때는 나의 당신이 아니었어요","artist":"신자원","lyric":"그토록 당신이라\n 불러보고 싶었는데\n 가슴깊이 숨겨둔채로\n 홀로 애만 태웠었네\n 사랑했던 기억들을 \n 내가슴에 남긴채\n 떠나는 당신 등뒤에\n 서투른 목소리로\n 당신이라 불렀었지만 "}]}