{"data":[{"url":"/artist/%EC%BD%94%EB%93%9C%EC%BF%A4%EC%8A%A4%ED%8A%B8/Born_from_the_Blue_Feat_JUSTHIS_%EC%98%A8%EC%8A%A4%ED%85%8C%EC%9D%B4%EC%A7%80_Ver/","subject":"Born from the Blue (Feat. JUSTHIS) (온스테이지 Ver.)","artist":"코드쿤스트","lyric":"Can we get a little break \n Can we get a little \n Can we get a little break \n 24/7 365 \n 노력하면 뭐든 이뤄낼"},{"url":"/artist/%EC%BD%94%EB%93%9C%EC%BF%A4%EC%8A%A4%ED%8A%B8/Lounge_Feat_%ED%99%94%EC%A7%80_%EC%98%A8%EC%8A%A4%ED%85%8C%EC%9D%B4%EC%A7%80_Ver/","subject":"Lounge (Feat. 화지) (온스테이지 Ver.)","artist":"코드쿤스트","lyric":"히피 같은 내 방랑을\n 다 받아줄 집시같은 너 내 여왕\n 아침이 밝으면 가방을 싸\n 저녁 전에 이미 활주로 떠나\n 같이 도망가자 바다 파랗고\n 저 데모 소리 안 들리는 곳\n 사람들"},{"url":"/artist/Sound_Offering/%EC%98%A4%EC%A7%81_%EC%84%B1%EB%A0%B9%EC%9D%B4/","subject":"오직 성령이","artist":"Sound Offering","lyric":"알기원해\n 나의 삶의 참된 의미를\n 가기원해\n 내가 가야 할 그 어딘가로\n 보기원해\n 어두움을 물리치는 빛\n 듣기원해\n 자유 얻은 내 친구의 웃음소리\n 오직 성령이 임하시면\n 너희"},{"url":"/artist/Sound_Offering/%EB%AF%B8%EB%AC%B8%EC%97%90%EC%84%9C/","subject":"미문에서","artist":"Sound Offering","lyric":"내 안에 그 누구도\n 빼앗을 수 없는 그 이름\n 그 이름 의지하여 나아갑니다\n 세상에 그 무엇도\n 대신 할 수 없는 그 이름\n 그 이름 믿음으로 선포합니다\n 은과 금은 내게 없으나"},{"url":"/artist/Luke_Faas/Shouldve_Seen_It/","subject":"Should`ve Seen It","artist":"Luke Faas","lyric":"I waited for an hour\n Before I drove to see you\n The very worst of feelings\n \n The interval that we "},{"url":"/artist/Luke_Faas/Why_Bother/","subject":"Why Bother","artist":"Luke Faas","lyric":"Why bother\n Why bother stretch my hand\n Why bother\n Why bother\n You for your demand\n My brother\n \n Y"},{"url":"/artist/Luke_Faas/Apathy/","subject":"Apathy","artist":"Luke Faas","lyric":"Can you take it\n I haven't made my mind\n I hope you own chapter\n So you can stay aligned\n So little "},{"url":"/artist/%EB%8F%84%EC%8B%9C%EC%88%98%EC%A1%B1%EA%B4%80/%EB%AF%B8%EB%81%BC/","subject":"미끼","artist":"도시수족관","lyric":"실 끝에 바늘에 욕망을 꾄다 \n 언제든 빠져나갈 수 있게 \n 내 끝에 욕망에 너로 사로잡을 때 \n 내 끝에 사랑에 너로 사로잡을 때 \n 행복하게 너도 웃고 있지 \n 비겁하게 너도 "},{"url":"/artist/%EB%8F%84%EC%8B%9C%EC%88%98%EC%A1%B1%EA%B4%80/%EC%BC%A0%EA%B9%80%EC%97%90_%EC%99%95%EA%B9%8C%EC%A7%80/","subject":"켠김에 왕까지","artist":"도시수족관","lyric":"배고픔에 시달리는 작은 노예여\n 어찌하여 너는 계속 여기 남았나\n 꿈이 너무 짙어 못 떠나는 노예여\n 언제까지 너는 꿈을 뜨지 못하나\n 부르튼 입술을 확인하며\n 어찌도 그리 슬피 "},{"url":"/artist/%EB%8F%84%EC%8B%9C%EC%88%98%EC%A1%B1%EA%B4%80/%ED%95%B4%ED%8C%8C%EB%A6%AC/","subject":"해파리","artist":"도시수족관","lyric":"새파란 물위에 투명한 사람 하나 \n 바다를 둥둥둥 하염없이 떠다니지 \n 그런 너나 이런 나나 \n 살아있는 시체나 같아 \n 그런 너는 내겐 나는 \n 너무나도 편안해 \n 차가운 유리 "}]}