{"data":[{"url":"/artist/%ED%99%98%ED%9D%AC/%EB%B0%98%EC%A7%9D%EC%9D%B8%EB%8B%A4/","subject":"반짝인다","artist":"환희","lyric":"언제부터 시작된 걸까 \n 니가 보고 싶어 뒤척인 날들 \n 어느새 너의 뒤를 걷고 있는 \n 내 발걸음 눈치챈 걸까 \n 내가 알던 세상은\n 반짝이진 않았는데\n 너로 인해 모든 게 빛이"},{"url":"/artist/KIRAVI/%EB%A7%88%EC%9D%8C/","subject":"마음","artist":"KIRAVI","lyric":"놀던 날 생각나\n 그 계절 구름 따라\n 둘이 웃던 날 그리워\n 그 시절 네 손을 잡았어\n 봄날엔 우리 함께\n 마주 앉아 끝을 읊겠지\n 끝말이 흩어질 때면\n 우리에 봄날도 그때\n 떠"},{"url":"/artist/KIRAVI/%EB%82%98%EC%9D%98_%EA%B0%88%EC%83%89_%EB%88%88_Feat_HOMEBOY/","subject":"나의 갈색 눈 (Feat. HOMEBOY)","artist":"KIRAVI","lyric":"울음소리에 나 커튼을 치네\n 넌 무얼 보고 누굴 봐\n 잠깐 어딜 봐\n 날 알고 싶어서 널 알고 싶었어\n 날 안고 싶어서 널 보려고 했어\n 그게 잘 안돼 갈색 눈을 가진\n 난 너에 "},{"url":"/artist/KIRAVI/today/","subject":"today","artist":"KIRAVI","lyric":"나 여기에 있어\n 널 크게 불러보고 싶어\n 따스했던 어제처럼\n 오늘도 뜨거울까\n 이 바람 따라\n 나 여기에 있어\n 널 크게 불러보고 싶어\n 따스했던 어제처럼\n 오늘도 뜨거울까\n 이"},{"url":"/artist/KIRAVI/%EB%82%A0_%EC%A2%8B%EC%9D%84_%EB%95%8C/","subject":"날 좋을 때","artist":"KIRAVI","lyric":"집에 가기 전에 날 봐요 \n 날 좋을 때 \n 해가 뜰 때 꽃 봐요 \n 맘 좋을 때 \n 그댄 알잖아 \n 모른 척 말아 \n 집에 가기 전에 날 봐요 \n 날 좋을 때 \n 해가 뜰 때 꽃"},{"url":"/artist/%EC%B2%B4%EB%A6%AC%ED%82%B4/Painter_Feat_Vteum_Bullet/","subject":"Painter (Feat. V.teum, Bullet)","artist":"체리킴","lyric":"난 성실한 화가\n 매일 너의 얼굴을 그리지\n 너만 있으면 난 너의\n 모든 것들을 그리고파\n 날 믿어줘 baby 너만 그려 매일매일\n beautiful girl 나와 이 곳에 둘이서"},{"url":"/artist/%EC%98%86%EC%86%8C_%EB%AC%B8%EB%B3%84_%EC%8A%AC%EA%B8%B0_%EC%9C%A0%EC%95%84_%EB%94%94%EC%95%A0%EB%82%98_%EC%86%8C%ED%9D%AC_%EC%88%98%EC%A0%95_%EC%86%8C%EB%AF%B8/Deep_Blue_Eyes_Prod_By_%EC%A7%84%EC%98%81_Inst/","subject":"Deep Blue Eyes (Prod. By 진영) (Inst.)","artist":"옆소 (문별, 슬기, 유아, 디애나, 소희, 수정, 소미)","lyric":"Deep blue Eyes \n 난 너의 눈을 바라보다 보면 \n 빨려 들어갈 것 같아 \n Deep blue Eyes \n 시크한 듯 부드러운 네 미소 \n 녹아 버릴 것만 같아 \n 나를"},{"url":"/artist/%EC%98%86%EC%86%8C_%EB%AC%B8%EB%B3%84_%EC%8A%AC%EA%B8%B0_%EC%9C%A0%EC%95%84_%EB%94%94%EC%95%A0%EB%82%98_%EC%86%8C%ED%9D%AC_%EC%88%98%EC%A0%95_%EC%86%8C%EB%AF%B8/Deep_Blue_Eyes_Prod_By_%EC%A7%84%EC%98%81/","subject":"Deep Blue Eyes (Prod. By 진영)","artist":"옆소 (문별, 슬기, 유아, 디애나, 소희, 수정, 소미)","lyric":"Deep blue Eyes \n 난 너의 눈을 바라보다 보면 \n 빨려 들어갈 것 같아 \n Deep blue Eyes \n 시크한 듯 부드러운 네 미소 \n 녹아 버릴 것만 같아 \n 나를"},{"url":"/artist/%EC%9D%B4%ED%98%B8%EC%9C%A4/You_Look_Stressed/","subject":"You Look Stressed","artist":"이호윤","lyric":"뭐든지\n 처음 시작할 땐 화려했을 거야\n 기억나니\n 거창하게 조잘거렸던 꿈들\n 기억 저 편으로 사라져버린\n 초롱초롱했던 눈빛\n 이젠 마치 동태 눈알 되어\n 파리 날리는 낡은 가판 "},{"url":"/artist/%EC%9D%B4%ED%98%B8%EC%9C%A4/%EB%B6%80%EC%A0%95_Trance/","subject":"부정 Trance","artist":"이호윤","lyric":"가랑비에 옷이 젖는지도 모르게\n 나도 모르는 사이 커져버린 무게에\n 멍한 표정으로 어깨 축쳐져 가지구\n 내가 괴로운 줄 몰랐어\n 외로운지 몰랐어\n I have been slowly"}]}