{"data":[{"url":"/artist/The_Moody_Blues/Cities/","subject":"Cities","artist":"The Moody Blues","lyric":"Neon, the city's sun\n Taxis like beetles run, and I see\n Pavements with yellow lines\n Grey walls and"},{"url":"/artist/The_Moody_Blues/Leave_This_Man_Alone/","subject":"Leave This Man Alone","artist":"The Moody Blues","lyric":"Ah, leave this man alone, Ah, leave this man alone\n \n Young girls with long faces come to me at nigh"},{"url":"/artist/The_Moody_Blues/Love_And_Beauty/","subject":"Love And Beauty","artist":"The Moody Blues","lyric":"I look around at other people\n I brush their shoulders at the corner of the street\n But all they not"},{"url":"/artist/The_Moody_Blues/Fly_Me_High/","subject":"Fly Me High","artist":"The Moody Blues","lyric":"I'm up to the eyes n' I love everyone\n Today I could cry I could reach for the sun\n I'm walking on a"},{"url":"/artist/Mutemath/Hit_Parade/","subject":"Hit Parade","artist":"Mutemath","lyric":"Here's a final straw to take a stride\n In a right direction\n I can hardly see the sky\n Covering this"},{"url":"/artist/Disiz_La_Peste/Vibe/","subject":"Vibe","artist":"Disiz La Peste","lyric":"Eh, DJ, mets moi un bon son, faut qu'j'serre cette go\n Un truc bien dansant, faut trop qu'j'aie cett"},{"url":"/artist/Bigflo__Oli/Personne/","subject":"Personne","artist":"Bigflo & Oli","lyric":"Yeah, Bigflo, Oli\n Tu connais non Ah\n \n J'voulais parler de ma ville et de ce monde qui va mal\n Parl"},{"url":"/artist/Lulu_Gainsbourg/Tequila/","subject":"Tequila","artist":"Lulu Gainsbourg","lyric":"Te quila je ne te connais pas\n Te tequila mais enfin qu'est ce que t'as\n Qu'est qui y a\n \n C'est une"},{"url":"/artist/Sfb/Badman_Flex_Feat_Jonna_Fraser/","subject":"Badman Flex (Feat. Jonna Fraser)","artist":"Sfb","lyric":"Badman\n Uno, two, tres\n What you sayyyy\n \n Kijk goed naar die badman flex en\n Ik laat je zien hoe ee"},{"url":"/artist/Nimo/Heute_mit_mir/","subject":"Heute mit mir","artist":"Nimo","lyric":"Jajajajajaja, jaaa\n Ey ey\n \n Hab' dich durch den ganzen Club verfolgt\n Und jetzt steh' ich vor dir u"}]}