{"data":[{"url":"/artist/%EC%A0%95%EC%9A%B0%EC%A7%84/%EC%83%88%EB%B2%BD_%EB%84%88%EC%97%90%EA%B2%8C/","subject":"새벽, 너에게","artist":"정우진","lyric":"차가운 새벽 공기를 지나 문득\n 그대 생각에 잠길 때면\n 아득하게 멀어져 버린 우리\n 그 사이가 너무도 아파요\n 사랑한단 그대의 말은 언제나\n 힘겨운 하루 그늘이 되어\n 조용하게 "},{"url":"/artist/%ED%94%8C%EB%9D%BC%EC%9B%8C/%EC%8B%9C%EC%A0%88%EC%97%B0%EC%9D%B8/","subject":"시절연인","artist":"플라워","lyric":"어김없이 오늘은 찾아와\n 너에게로 가는 이 길이\n 왠지 힘겹지만\n 웃으며 널 보내주는 게\n 나의 마지막 선물인 걸 알기에\n 많은 축복 속에서\n 나를 찾지는 마\n 여전히 아름다운 너"},{"url":"/artist/%EA%B8%88%EC%9E%94%EB%94%94/%EB%B3%B4%EC%95%BD%EA%B0%99%EC%9D%80_%EC%B9%9C%EA%B5%AC/","subject":"보약같은 친구","artist":"금잔디","lyric":"같이 가세 같이 가세 \n 보약같은 친구 \n 같이 가세 \n 같이 가세 \n 보약같은 친구야 \n 같이 가세 \n 아침에 눈을 뜨면 \n 제일 먼저 생각나는 \n 자네는 좋은 친구야 \n 보약같"},{"url":"/artist/%EC%9D%B4%EC%9C%A0%EC%84%B1/%EB%BD%80%EB%BD%80_Feat_%EC%A4%80%ED%98%B8_%EC%86%A1%ED%9E%88/","subject":"뽀뽀 (Feat. 준호, 송히)","artist":"이유성","lyric":"내가 밥 사고 커피도 샀는데\n 뽀뽀 한번만 해줘\n 아침부터 너 따라다녔는데\n 뽀뽀로 날 보내줘\n 나는 많은 거 바라지 않아\n 크고 비싼 건 필요도 없어\n 깊고 진한 건 기대도 안 "},{"url":"/artist/%EC%9E%A5%EA%B2%BD%ED%9B%88/%EC%97%AC%EB%A6%84_%EC%95%84%EC%9D%B4/","subject":"여름 아이","artist":"장경훈","lyric":"넌 참 착한 아이야\n 내가 좋아하는건 다 해주려 해\n 넌 참 예쁜 아이야\n 네가 싫어하는것도 같이 먹어줘\n 귀찮은 것도 같이 해주고\n 나와 함께 고민해주는 너에게\n 소나기처럼 흠뻑"},{"url":"/artist/Midnight_Oil/Pictures_Live_at_The_Narrabeen_Sands_Hotel_1996/","subject":"Pictures (Live at The Narrabeen Sands Hotel 1996)","artist":"Midnight Oil","lyric":"I just want to see that clear clear ight\n Don't want to be a member of a species that's deceasing\n K"},{"url":"/artist/Midnight_Oil/Powderworks_Live_at_Tanelorn_Music_Festival_1981/","subject":"Powderworks (Live at Tanelorn Music Festival 1981)","artist":"Midnight Oil","lyric":"There's a shit storm a'coming\n I feel it coming soon\n There's a time and a place\n And a moment in sp"},{"url":"/artist/Midnight_Oil/Dont_Wanna_Be_the_One_Live_at_Tanelorn_Music_Festival_1981/","subject":"Don`t Wanna Be the One (Live at Tanelorn Music Festival 1981)","artist":"Midnight Oil","lyric":"I'm an innocent victim, I'm just like you\n We end up in home units with a brick wall view\n I can't b"},{"url":"/artist/Midnight_Oil/Section_5_Bus_to_Bondi_Live_at_Tanelorn_Music_Festival_1981/","subject":"Section 5 Bus to Bondi (Live at Tanelorn Music Festival 1981)","artist":"Midnight Oil","lyric":"Push start that car tomorrow\n I'll take it to the tip yard\n Well I'll leave it as a metal wreck\n For"},{"url":"/artist/Midnight_Oil/Koala_Sprint_Live_at_Tanelorn_Music_Festival_1981/","subject":"Koala Sprint (Live at Tanelorn Music Festival 1981)","artist":"Midnight Oil","lyric":"And out from the echoes of the night\n Concrete caverns catch the sky and hold the stars to ransom\n A"}]}