{"data":[{"url":"/artist/Warren_Zevon/Werewolves_Of_London/","subject":"Werewolves Of London","artist":"Warren Zevon","lyric":"I saw a werewolf with a Chinese menu in his hand\n Walking through the streets of Soho in the rain\n H"},{"url":"/artist/Marc_Cohn/Walking_In_Memphis/","subject":"Walking In Memphis","artist":"Marc Cohn","lyric":"Put on my blue suede shoes\n And I boarded the plane\n Touched down in the land of the Delta Blues\n In"},{"url":"/artist/Chicago/Youre_The_Inspiration/","subject":"You`re The Inspiration","artist":"Chicago","lyric":"You know our love was meant to be\n The kind of love that lasts forever\n And I want you here with me\n"},{"url":"/artist/MrBig/To_Be_With_You/","subject":"To Be With You","artist":"Mr.Big","lyric":"Hold on, little girl\n Show me what he's done to you\n Stand up, little girl\n A broken heart can't be "},{"url":"/artist/Harry_Chapin/Cats_In_The_Cradle/","subject":"Cats In The Cradle","artist":"Harry Chapin","lyric":"My child arrived just the other day\n He came to the world in the usual way\n But there were planes to"},{"url":"/artist/Little_Feat/Willin/","subject":"Willin`","artist":"Little Feat","lyric":"I been warped by the rain\n Driven by the snow\n I'm drunk and dirty, don't ya know\n And I'm still, oh"},{"url":"/artist/Love/Alone_Again_Or_LP_Ver/","subject":"Alone Again Or (LP Ver.)","artist":"Love","lyric":"Yeah\n Said it's all right\n I won't forget\n All the times I've waited patiently for you\n And you'll d"},{"url":"/artist/The_Grateful_Dead/Touch_Of_Grey/","subject":"Touch Of Grey","artist":"The Grateful Dead","lyric":"Must be getting early\n Clocks are running late\n Paint by number morning sky looks so phony\n Dawn is "},{"url":"/artist/White_Lion/When_The_Children_Cry/","subject":"When The Children Cry","artist":"White Lion","lyric":"Little child dry your crying eyes\n How can I explain the fear you feel inside\n Cause you were born i"},{"url":"/artist/Janes_Addiction/Jane_Says/","subject":"Jane Says","artist":"Jane`s Addiction","lyric":"Jane says\n I'm done with Sergio\n He treats me like a ragdoll\n She hides the television\n Says I don't"}]}