{"data":[{"url":"/artist/%EA%B9%80%ED%98%9C%EA%B4%91/%EC%B0%A9%EA%B0%81/","subject":"착각","artist":"김혜광","lyric":"아니겠지\n 한 번 더 날 다그치고\n 신경 쓰지 않겠다고\n 네가 있는 곳으로 가지만\n 은근히 날 향한 행동 같은\n 너 혹시 나를 아나\n 내가 이상한 건가\n 나에게 말해봐 널 알길 원"},{"url":"/artist/%EA%B9%80%ED%83%9C%EC%9C%A4/%EC%95%8C%EA%B3%A0%EC%9E%88%EB%82%98%EC%9A%94/","subject":"알고있나요","artist":"김태윤","lyric":"그대 소식이 가끔씩 들려올 때면\n 그대는 이제 다 잊었단 생각이 들면\n 그대가 미워져요\n 난 아직 그대론데\n 늦은 후회는 그리움이 돼 가요\n 얼어붙었던 내 맘이 녹으면\n 여전히 그"},{"url":"/artist/%EA%B3%BD%EC%B0%AC%EB%B9%84/%EC%8B%A0%EB%B0%9C%EC%9E%A5/","subject":"신발장","artist":"곽찬비","lyric":"오늘도 난\n 신발장 앞에서\n 외출을 준비해\n 작년 이맘때\n 운동화를 꺼내\n 한참을 멍하니 봤어\n 맘에 쏙 들던\n 낡지도 않은\n 네가 예전 같지 않아서\n 변한 거 없이\n 넌 그대로인"},{"url":"/artist/%EC%97%90%ED%94%BC%ED%83%80%EC%9D%B4%EC%A0%80_Appetizer/%EB%B3%B4%EA%B3%A0_%EC%8B%B6%EC%96%B4%EC%A7%80%EB%8A%94_%EB%B0%A4%EC%97%90_Inst/","subject":"보고 싶어지는 밤에 (Inst.)","artist":"에피타이저 (Appetizer)","lyric":"모든 게 이제 사라져 \n 혼자 남겨져\n 더 아프게 느껴지는데 \n 눈물이 날만큼\n 보고 싶어지는 밤에 \n 아무것도 할 수 없어\n 더욱 그리워지는 늦은 저녁 \n 공허한 마음 그 속에서"},{"url":"/artist/%EC%97%90%ED%94%BC%ED%83%80%EC%9D%B4%EC%A0%80_Appetizer/%EB%B3%B4%EA%B3%A0_%EC%8B%B6%EC%96%B4%EC%A7%80%EB%8A%94_%EB%B0%A4%EC%97%90_Feat_%EB%AA%A8%EB%8B%9D%EC%BB%A4%ED%94%BC/","subject":"보고 싶어지는 밤에 (Feat. 모닝커피)","artist":"에피타이저 (Appetizer)","lyric":"모든 게 이제 사라져 \n 혼자 남겨져\n 더 아프게 느껴지는데 \n 눈물이 날만큼\n 보고 싶어지는 밤에 \n 아무것도 할 수 없어\n 더욱 그리워지는 늦은 저녁 \n 공허한 마음 그 속에서"},{"url":"/artist/%EB%8B%A8%EC%B6%94_Danxhu/Mono_Drama_Feat_%EA%B0%80%EC%97%B0/","subject":"Mono Drama (Feat. 가연)","artist":"단추 (Danxhu)","lyric":"아마 우린 막바지 기억에 \n 다다르고 있는 것 같아서 불안해 \n 이별은 아프고 \n 후회는 후회가 될 테고 \n 미련은 미련처럼 남겠지 \n 신경도 못써 \n 나도 지쳐버린 내 일상에 \n"},{"url":"/artist/%EC%9E%90%EC%BF%A4_JaKun/My_Ideal_Type_Feat_%EC%B2%A0%ED%9B%88/","subject":"My Ideal Type (Feat. 철훈)","artist":"자쿤 (JaKun)","lyric":"꿈만 같은 널 만났던 것부터\n 내 옆에 있는 넌 천사같아\n 아직 넌 날 잘모르겠지만\n 분명 넌 곧 알게 될꺼야 넌\n 내가 그렇게 할게\n 넌 거기 서 있기만 해\n 우연히 길거리에서 "},{"url":"/artist/%ED%95%98%EC%9D%B4%ED%8F%AC%ED%85%9C%ED%94%84_Hypotemp/Get_My_Mind_Straight/","subject":"Get My Mind Straight","artist":"하이포템프 (Hypotemp)","lyric":"Get your get my mind straigh \n Get your get my mind straigh \n Get your get my mind straigh \n Get you"},{"url":"/artist/%ED%95%98%EC%9D%B4%ED%8F%AC%ED%85%9C%ED%94%84_Hypotemp/Makes_Me_Higher_Feat_KOODANHYO/","subject":"Makes Me Higher (Feat. KOODANHYO)","artist":"하이포템프 (Hypotemp)","lyric":"I make people love this\n 앞에서 들었지\n It's not a bull shit\n 어릴 때부터 자란 china\n 사람들은 광장에서 춤을 췄네\n 아님 아무곳이나\n "},{"url":"/artist/PinkPlum_%ED%95%91%ED%81%AC%ED%94%8C%EB%9F%BC/%EA%BD%83%EA%B5%AC%EA%B2%BD_%EA%B0%80%EC%9A%94/","subject":"꽃구경 가요","artist":"PinkPlum (핑크플럼)","lyric":"너와 난 왜이리 바쁜가요\n 하필 이렇게 사랑스러운 날씨에\n 지금 당장 손잡고 \n 달려나가야 하는데\n 이러다 저러다 비가 오기 전에\n 꽃구경 가요 꽃구경 가요\n 꽃구경 가요\n 주먹밥"}]}