{"data":[{"url":"/artist/The_Yardbirds/I_Wish_You_Would_Feat_Eric_Clapton/","subject":"I Wish You Would (Feat. Eric Clapton)","artist":"The Yardbirds","lyric":"Early in the morning, 'bout the break of day\n That's when my baby went away\n Come back, baby, I wish"},{"url":"/artist/The_Yardbirds/Pretty_Girl_Feat_Eric_Clapton/","subject":"Pretty Girl (Feat. Eric Clapton)","artist":"The Yardbirds","lyric":"Pretty girl, damn shame\n You let those homely girls come and take your man\n Pretty baby, well, you k"},{"url":"/artist/The_Yardbirds/Here_Tis_Feat_Eric_Clapton/","subject":"Here `Tis (Feat. Eric Clapton)","artist":"The Yardbirds","lyric":"Whoa, whoa, whoa\n Whoa, whoa, whoa\n I said whoa, whoa, whoa\n Whoa, whoa, whoa\n I love my baby\n Whoa,"},{"url":"/artist/The_Yardbirds/Im_A_Man_Feat_Eric_Clapton/","subject":"I`m A Man (Feat. Eric Clapton)","artist":"The Yardbirds","lyric":"Now when I was a little boy\n At the age of five\n I had somethin' in my pocket\n Kept a lot of folks a"},{"url":"/artist/The_Yardbirds/Got_Love_If_You_Want_It_Feat_Eric_Clapton/","subject":"Got Love If You Want It (Feat. Eric Clapton)","artist":"The Yardbirds","lyric":"Got love if you want it, babe\n Got love if you want it, babe\n Got love if you want it\n Got love if y"},{"url":"/artist/The_Yardbirds/I_Aint_Got_You_Feat_Eric_Clapton/","subject":"I Ain`t Got You (Feat. Eric Clapton)","artist":"The Yardbirds","lyric":"I got a Maserati GT\n With snakeskin upholstery\n I got a charge account at Goldblatt's\n But I ain't g"},{"url":"/artist/The_Yardbirds/Good_Morning_Little_Schoolgirl_Feat_Eric_Clapton/","subject":"Good Morning Little Schoolgirl (Feat. Eric Clapton)","artist":"The Yardbirds","lyric":"Good morning, little schoolgirl\n Good morning, little schoolgirl\n Can I go home with you\n Won't you "},{"url":"/artist/The_Yardbirds/For_Your_Love_Feat_Eric_Clapton/","subject":"For Your Love (Feat. Eric Clapton)","artist":"The Yardbirds","lyric":"For your love\n For your love\n For your love\n I'd give you everything and more, and that's for sure\n "},{"url":"/artist/%EB%8F%99%EC%9A%94%EB%86%80%EC%9D%B4/%EC%82%BC%EA%B3%84%ED%83%95%EC%86%A1/","subject":"삼계탕송","artist":"동요놀이","lyric":"삼계탕을 먹어보세요\n 정말로 맛있어\n 대추랑 인삼도 넣고\n 맛있게 끓여요\n \n 찹쌀밥도 너무 맛있죠\n 속이 풀어져요\n 따뜻한 국물 먹으면\n 속이 든든해요\n \n 부드러운 닭고기를\n "},{"url":"/artist/%EB%85%B8%ED%81%AC/%EB%B9%84%EC%B6%B0%EC%A4%80%EB%8B%A4/","subject":"비춰준다","artist":"노크","lyric":"바람들이 떠난 밤에\n 나는 여기 혼자 있는데 \n 누가 날 데려다 논건지\n 착한 이 밤에 \n 내 맘속에 작은 기분이\n 날 두고 떠나 가버렸는지\n 아직도 저 달은 \n 날 바라보기만 하"}]}