{"data":[{"url":"/artist/%EA%B9%80%ED%98%81%EA%B1%B4/%EA%B0%80%EC%88%98%EA%B0%80_%EB%90%98%EB%8B%A4/","subject":"가수가 되다","artist":"김혁건","lyric":"\n  어릴 적 나는 키 작고 공부도 못하고, 잘하는 거라고는 뛰어 노는 일 밖에 없었던 아이였다. 공부 잘하고 착한 형과 누나가 있었기에 막내였던 나는 마음껏 자유를 누릴 수 있었"},{"url":"/artist/%EA%B9%80%ED%98%81%EA%B1%B4/%EC%9D%B8%ED%8A%B8%EB%A1%9C/","subject":"인트로","artist":"김혁건","lyric":"\n “어… 어… ”\n “엄마 나 있잖아”\n “사… 사…”\n “사람을 친 것 같아”\n “사… 살려…”\n “난 괜찮은데 저 사람이 다친 것 같아”\n  … 차에 부딪혔다. 심술궂은 아이"},{"url":"/artist/%EA%B9%80%ED%98%81%EA%B1%B4/%ED%94%84%EB%A1%A4%EB%A1%9C%EA%B7%B8_2/","subject":"프롤로그 2","artist":"김혁건","lyric":"\n  눈부신 조명 아래 세상의 자유를 노래하던 남자\n 잔인한 어느 봄날, 그는 차가운 도로 위에 쓰러져 사지마비 판정을 받았다. 세상은 그에게 더는 두발로 서지도, 노래를 부르지도"},{"url":"/artist/%EA%B9%80%ED%98%81%EA%B1%B4/%ED%94%84%EB%A1%A4%EB%A1%9C%EA%B7%B8_1/","subject":"프롤로그 1","artist":"김혁건","lyric":"\n  ‘살아있지만 죽음보다 못한 삶, 죽고 싶지만 혼자서는 죽지도 못하는 상태’ 그렇게 수년의 시간을 보냈다.\n  어느 날 갑자기 찾아온 사지마비 장애에 맞닥뜨려 부정, 분노, 우"},{"url":"/artist/JUNIEL/Last_Carnival_Inst/","subject":"Last Carnival (Inst.)","artist":"JUNIEL","lyric":"BPM 175 깨진 조명등과 \n Just close my eyes \n 붉게 물든 머리칼 그 속에 난 \n The scene is printed on \n 그 씬을 지울 수는 없겠지 a"},{"url":"/artist/JUNIEL/Last_Carnival/","subject":"Last Carnival","artist":"JUNIEL","lyric":"BPM 175 깨진 조명등과 \n Just close my eyes \n 붉게 물든 머리칼 그 속에 난 \n The scene is printed on \n 그 씬을 지울 수는 없겠지 a"},{"url":"/artist/Gryffin/Love_In_Ruins_Feat_Sinead_Harnett/","subject":"Love In Ruins (Feat. Sinead Harnett)","artist":"Gryffin","lyric":"Show me how we move\n Now I'm learning\n Three is more than two\n You are the one I see\n You are a half"},{"url":"/artist/Nick_Mulvey/Mountain_To_Move/","subject":"Mountain To Move","artist":"Nick Mulvey","lyric":"Yeah, oh\n \n Caught up in specialness\n I wish you could see that we are kings of bliss\n Begging for m"},{"url":"/artist/Sido/Bis_ich_nicht_mehr_bin/","subject":"Bis ich nicht mehr bin","artist":"Sido","lyric":"100000 Menschen, mit 200000 Handen und der Rest macht auf beleidigt\n Weil das hier noch nicht vorbei"},{"url":"/artist/Sido/Nobody_Feat_Chiddy_Bang__MoTrip/","subject":"Nobody (Feat. Chiddy Bang & MoTrip)","artist":"Sido","lyric":"Mir ist scheißegal, was du so getan hast\n Wir beide reden erst, wenn du 'ne Hublot am Arm hast\n Der "}]}