{"data":[{"url":"/artist/%EB%9D%BC%EC%9D%B4%EC%A6%88/%EB%B9%84%EA%B0%80_%E6%82%B2%E6%AD%8C/","subject":"비가 (悲歌)","artist":"라이즈","lyric":"오랜 시간이 지나도 흠\n 너의 잔상은 내게 남아\n 많은 계절은 지나도\n 너를 지나갈 수 없다\n 왜 돌아오지 않는 시간만\n 빛나고 내 마음을 부수고\n 내 기억을 훔치는지\n 나는 걸어"},{"url":"/artist/%EB%9D%BC%EC%9D%B4%EC%A6%88/%EB%8B%AC%EC%9D%98_%EA%BD%83_Concert_Ver/","subject":"달의 꽃 (Concert Ver.)","artist":"라이즈","lyric":"바람이 불면\n 내 마음 꽃잎하나 날아가고\n 어느덧 흐른 눈물이\n 내 입술을 적셔주네\n 조용한 바람 애달픔\n 달래주어 감싸주고\n 가슴 속 깊은 바닷가\n 저 별들을 빛내주네\n 달빛에 "},{"url":"/artist/Joakim_Lundell/All_I_Need_Feat_Arrhult/","subject":"All I Need (Feat. Arrhult)","artist":"Joakim Lundell","lyric":"Under water\n I feel like I'm under water\n Cause I can't get to you\n Moving closer, but can't seem to"},{"url":"/artist/%EC%88%98%EB%9E%80_SURAN/%EB%B0%94%EB%9E%8C%EC%9D%B4_%EC%B0%A8%EA%B0%91%EB%84%A4%EC%9A%94_Inst/","subject":"바람이 차갑네요 (Inst.)","artist":"수란 (SURAN)","lyric":"바람이 차갑네요 \n 오늘따라 고된 하루였죠\n 혼자 걷는 길 끝에 \n 항상 올려다보던 저 달빛도\n 내 맘 같지 않죠 \n 그대 하나 없을 뿐인데\n 숨도 못 쉴 만큼 \n 다 내려놓고 싶"},{"url":"/artist/%EC%88%98%EB%9E%80_SURAN/%EB%B0%94%EB%9E%8C%EC%9D%B4_%EC%B0%A8%EA%B0%91%EB%84%A4%EC%9A%94/","subject":"바람이 차갑네요","artist":"수란 (SURAN)","lyric":"바람이 차갑네요 \n 오늘따라 고된 하루였죠\n 혼자 걷는 길 끝에 \n 항상 올려다보던 저 달빛도\n 내 맘 같지 않죠 \n 그대 하나 없을 뿐인데\n 숨도 못 쉴 만큼 \n 다 내려놓고 싶"},{"url":"/artist/%EB%B0%95%ED%9B%88/%EB%84%8C_%EB%82%98%EC%9D%98_%EB%A1%9C%EB%98%90_Remix_Feat_%EA%B9%80%ED%98%84%EC%B2%A0/","subject":"넌 나의 로또 Remix (Feat. 김현철)","artist":"박훈","lyric":"이 세상의 사람들 로또 로또\n 로또 한 번 돼보자고\n 매 주 마다 얼마나\n 심장 떨며 사는가\n 돈이 뭐니뭐니해도 최고라지만\n 그 보다 더 소중한 건\n 사랑하는 내 사람과\n 알콩달콩"},{"url":"/artist/%EC%9A%A9%EC%9A%A9%EC%9D%B4_X_%ED%99%94%EC%88%98/%EC%A7%80%EC%98%81%EC%9D%B4%EC%97%90%EA%B2%8C/","subject":"지영이에게","artist":"용용이 X 화수","lyric":"그대 곁에 내 사랑 \n 언제나 영원하죠 \n 이대로 평생토록 \n 그대와 긴 여행을 떠나가요 \n 당신은 변치 마오 \n 우리사랑 그대 모습 \n 이제는 내 곁에서 \n 행복해요 영원히 그대"},{"url":"/artist/HUS_%ED%97%88%EB%B0%8D%EC%96%B4%EB%B0%98%EC%8A%A4%ED%85%8C%EB%A0%88%EC%98%A4/Milky_Way/","subject":"Milky Way","artist":"HUS (허밍어반스테레오)","lyric":"오빠라 부르는건 평범해\n 애칭을 만들어 볼까\n 아무거나 나 그냥은 No\n 여자들은 그런 대답 제일 싫어해\n 띵동 띵동 띵동 띵동 띵동 띵동\n 나의 벨이 울려라\n 참깨 참깨 참깨 참"},{"url":"/artist/Sia/Chandelier/","subject":"Chandelier","artist":"Sia","lyric":"Party girls don't get hurt \n Can't feel anything \n when will I learn \n I push it down push it down\n "},{"url":"/artist/One_Direction/AM/","subject":"A.M.","artist":"One Direction","lyric":"Won't you stay 'til the A.M\n All my favourite conversations\n Always made in the A.M\n yeah yeah\n Feel"}]}