{"data":[{"url":"/artist/Riddim_Commission/Cut_Some_Shapes_Radio_Edit/","subject":"Cut Some Shapes (Radio Edit)","artist":"Riddim Commission","lyric":"That's right\n Scrufizzer and Neutrino\n Yeah, Super Neuch\n Srufizzer and Neutrino\n That's right\n Ridd"},{"url":"/artist/Boogie_%EB%B6%80%EA%B8%B0/%EC%98%A4%EB%8A%98_%EC%96%B4%EB%95%8C/","subject":"오늘 어때","artist":"Boogie (부기)","lyric":"How are you feeling today\n Hey 오늘 하루 어때\n 이것도 저것도 다 하고픈데 Woh\n Hey 오늘 하루 어때 어때 Come on Ahhh\n Let's get"},{"url":"/artist/%EB%8F%99%EC%9A%94/%EC%A6%90%EA%B1%B0%EC%9A%B4_%EB%82%98%EC%9D%98_%EC%A7%91/","subject":"즐거운 나의 집","artist":"동요","lyric":"즐거운 곳에서는 날 오라 하여도 \n 내 쉴 곳은 작은 집 내 집분이리\n 내 나라 내 기쁨 길이 쉴 곳도\n 꽃 피고 새 우는 내 집뿐이리\n 오 사랑 나의 집 \n 즐거운 나의 벗 내 "},{"url":"/artist/HOONIA_%ED%9B%84%EB%8B%88%EC%95%84/%EC%96%98%EC%A7%80/","subject":"얘지","artist":"HOONIA (후니아)","lyric":"Oh I feel you all the time \n 쉽게 사랑에 빠지는 type은\n 아니지만 넌 달라\n 아직 널 난 잘 모르지만\n 괜찮아 조금씩 알아가도\n 늦지 않을텐데 우린 급해"},{"url":"/artist/KUCCI/GET_IT_Inst/","subject":"GET IT (Inst.)","artist":"KUCCI","lyric":"Cause I get it I get it I go \n If you with it you with it I saw \n I'm in the mood for money making \n"},{"url":"/artist/KUCCI/GET_IT_Feat_Okasian/","subject":"GET IT (Feat. Okasian)","artist":"KUCCI","lyric":"Cause I get it I get it I go \n If you with it you with it I saw \n I'm in the mood for money making \n"},{"url":"/artist/%EC%A0%9C%EC%9D%B4%ED%88%AC/%EB%A7%90%ED%95%B4_%EB%B4%90/","subject":"말해 봐","artist":"제이투","lyric":"두려워하는 이유가 무언가\n 그렇게 주저앉아 있는\n 이유는 뭔가\n 시간이 너무 아깝지 않은가\n 어느새 눈뜨면 지나 버린 날들\n 말해봐 네가 원하는 게\n 도대체 뭔지\n 무엇이 문제인 "},{"url":"/artist/%EC%9D%B4%EC%84%B8%EC%98%81/%EB%85%B8%EB%9E%98%EB%A1%9C_%ED%95%98%EB%8A%94_%EA%B3%A0%EB%B0%B1/","subject":"노래로 하는 고백","artist":"이세영","lyric":"조금은 어색해 이 공간이 \n 너에게 말해줄 비밀처럼 \n 사랑이란 모르지만 \n 오 너에 대한 설레임 같아 \n 아직은 너에게 말 못했어 \n 떨리는 입술이 불안해서 그래\n 네 앞에 고백"},{"url":"/artist/%ED%8B%B0%EC%95%84%EB%9D%BC/My_Love/","subject":"My Love","artist":"티아라","lyric":"이렇게 넌 또 왜 날 아프게만 하는데\n 날 떠나려고 하는데 \n 나를 그렇게도 몰라 몰라\n baby \n 니가 뭔데 날 자꾸 울리려만 하는데\n 날 돌아서려 하는데 \n 왜 아직도 날 아"},{"url":"/artist/%EC%B0%BD%EB%AA%A8_CHANGMO/I_Always/","subject":"I Always","artist":"창모 (CHANGMO)","lyric":"여전히 너를 보면\n 잠들은 너를 보면\n 우리 처음 만남이 생각나\n 그댄 여전히 아름다워\n 여전히 너를 보면\n 잠들은 너를 보면\n 우리 처음 만남이 생각나\n 그댄 여전히 사랑스러워\n"}]}