{"data":[{"url":"/artist/Kid_Cudi/Wounds/","subject":"Wounds","artist":"Kid Cudi","lyric":"Wee ooo, wee ooo, wee ooo, wee ooo, wee ooo\n Oh, wee ooo, oh wee ooo\n \n Hmmm, of course we all have "},{"url":"/artist/Kid_Cudi/Distant_Fantasies/","subject":"Distant Fantasies","artist":"Kid Cudi","lyric":"Hey ey ey ey ey, uh\n Hey ey ey ey ey, uh\n You frontin' for that new nigga and, and we know it, hmmm\n"},{"url":"/artist/Kid_Cudi/Dance_4_Eternity/","subject":"Dance 4 Eternity","artist":"Kid Cudi","lyric":"Hey, it's so hard to trust anyone\n Hmm, so this is awesome\n You got me smiling, yeah you're a lot of"},{"url":"/artist/Kid_Cudi/Flight_At_First_Sight___Advanced_Feat_Pharrell_Williams/","subject":"Flight At First Sight / Advanced (Feat. Pharrell Williams)","artist":"Kid Cudi","lyric":"Mmm, mmm, mmm, I like that\n I'm into it I like that\n She's a hypnotist I like that\n And I'm on the l"},{"url":"/artist/Kid_Cudi/Baptized_In_Fire_Feat_Travis_Scott/","subject":"Baptized In Fire (Feat. Travis Scott)","artist":"Kid Cudi","lyric":"Easy, back up, back up, back up\n Turn your radio, turn your radio, off\n Watch me now, baby, baby\n Uh"},{"url":"/artist/Kid_Cudi/Rose_Golden_Feat_Willow_Smith/","subject":"Rose Golden (Feat. Willow Smith)","artist":"Kid Cudi","lyric":"Two, three, four\n Ohhh oh ohh\n \n Oh, since I was young, been grooving to my own drum\n Ain't that man"},{"url":"/artist/Kid_Cudi/ILLusions/","subject":"ILLusions","artist":"Kid Cudi","lyric":"These illusions in my head, ohh I never wanna leave\n Hallucinating, flying through air, ohh, so long"},{"url":"/artist/Kid_Cudi/All_In/","subject":"All In","artist":"Kid Cudi","lyric":"Ohhhh, ahhhh\n Ohhhh, ohhhh\n Ummmm, ohhhh\n \n Hold on let me explain\n Sometimes I just don't know what"},{"url":"/artist/Kid_Cudi/By_Design_Feat_Andre_Benjamin/","subject":"By Design (Feat. Andre Benjamin)","artist":"Kid Cudi","lyric":"Oooh, tap in to the frequency, love\n Oooh, tap in to the frequency, love\n \n Fall from dusk to dawn, "},{"url":"/artist/Kid_Cudi/Releaser/","subject":"Releaser","artist":"Kid Cudi","lyric":"You knew you'd find me Hmm, hmm\n You knew just where to find me Hmm, hmm\n Hmm, hmm\n J'aime beaucoup,"}]}