{"data":[{"url":"/artist/AVOID_X_JUNG_YOUNG/%EC%82%AC%EB%9E%91%EC%9D%80_%ED%83%80%EC%9D%B4%EB%B0%8D_Feat_Lobo_Da_King/","subject":"사랑은 타이밍 (Feat. Lobo Da King)","artist":"AVOID X JUNG YOUNG","lyric":"오늘 약속이 있었는데 \n 그게 마침 너네 집 근처\n 오늘 날씨도 좋고 왠지 느낌도 좋아\n 나오라고 문자를 할까 \n 아니면 전화로 할까\n 이러다 또 타이밍만 놓치겠네\n 사랑은 타이밍"},{"url":"/artist/Away/Sleepwalker_Feat_London_Thor/","subject":"Sleepwalker (Feat. London Thor)","artist":"Away","lyric":"Sleepwalker\n You enter my dreams\n When I drift off\n \n You keep out the bad\n Things\n \n I'm not afraid"},{"url":"/artist/%EC%B5%9C%EC%8B%A0%ED%9E%9B%ED%8A%B8_%EC%9C%A0%EC%B9%98%EC%9B%90__%EC%96%B4%EB%A6%B0%EC%9D%B4%EC%A7%91_%EC%9D%B8%EA%B8%B0%EB%8F%99%EC%9A%94_%EC%9C%A0%EC%95%84%EB%8F%99%EC%9A%94_%EC%B5%9C%EC%8B%A0%EB%A7%8C%ED%99%94%EB%8F%99%EC%9A%94/%EA%BC%AD_%EC%95%88%EC%95%84_%EC%A4%84%EB%9E%98%EC%9A%94_KBS_%EC%B0%BD%EC%9E%91%EB%8F%99%EC%9A%94%EC%A0%9C_%EB%8C%80%EC%83%81/","subject":"꼭 안아 줄래요 (KBS 창작동요제 `대상`)","artist":"","lyric":"꼭 안아줄래요\n 내 친구 아픈 마음을 \n 내가 속상할때 누군가 그랬던것처럼\n 친구의 잘못은 따뜻한 용서로 안아주고\n 친구의 실수도 이해로 안아줄래요\n 어쩌다 생긴 미움은 어떻할까\n"},{"url":"/artist/Keith_Jarrett/How_About_You/","subject":"How About You","artist":"Keith Jarrett","lyric":"When a girl meets boy\n Life can be a joy\n But the note they end on\n Will depend on\n Little pleasures"},{"url":"/artist/Keith_Jarrett/No_Lonely_Nights/","subject":"No Lonely Nights","artist":"Keith Jarrett","lyric":"The little girl standing in the rain\n On the corner of 42nd street\n And she's all alone on the bad s"},{"url":"/artist/Keith_Jarrett/Youd_Be_So_Nice_To_Come_Home_To/","subject":"You`d Be So Nice To Come Home To","artist":"Keith Jarrett","lyric":"You'd be so nice to come home to\n You'd be so nice by the fire\n While the breeze on high, sang a lul"},{"url":"/artist/Keith_Jarrett/Dont_Ever_Leave_Me/","subject":"Don`t Ever Leave Me","artist":"Keith Jarrett","lyric":"I was created for one man alone\n It wasn't easy to find\n Now that I've found him, I wonder just how\n"},{"url":"/artist/Keith_Jarrett/Things_Aint_What_They_Used_To_Be/","subject":"Things Ain`t What They Used To Be","artist":"Keith Jarrett","lyric":"I am not such a clever one\n About the latest fads\n I admit I was never one\n Adored by local lads\n No"},{"url":"/artist/Keith_Jarrett/Imagination/","subject":"Imagination","artist":"Keith Jarrett","lyric":"Magic mirror come and search my heart\n Can you tell me what you see\n There's a thousand voices whisp"},{"url":"/artist/Keith_Jarrett/Autumn_Leaves/","subject":"Autumn Leaves","artist":"Keith Jarrett","lyric":"The falling leaves drift by the window\n The autumn leaves of red and gold\n I see your lips, the summ"}]}