{"data":[{"url":"/artist/Zucchero/13_Buone_Ragioni/","subject":"13 Buone Ragioni","artist":"Zucchero","lyric":"Ecco 13 buone ragioni\n Per preferire una birra\n A una come te\n E un panino al salame\n \n Ecco 13 buon"},{"url":"/artist/Zucchero/Partigiano_Reggiano/","subject":"Partigiano Reggiano","artist":"Zucchero","lyric":"Black cat my bone\n Un po' di slempito, boom boom\n Black cat ma belle\n Le insidie pullulano bang bang"},{"url":"/artist/The_Fat_Rat/Monody_Radio_Edit_Feat_Laura_Brehm/","subject":"Monody (Radio Edit) (Feat. Laura Brehm)","artist":"The Fat Rat","lyric":"here we stand opHere we stand open arms \n \n \n \n ？우린 여기 두 팔을 벌리고 서있어\n \n \n \n This is home where we are"},{"url":"/artist/Charlie_Gronvall/Running_Wild/","subject":"Running Wild","artist":"Charlie Gronvall","lyric":"I'm a fool, a clown, a joker\n That's right\n With your head against my shoulder\n \n you lied so good\n "},{"url":"/artist/2B1/%EC%B6%95%EA%B0%80/","subject":"축가","artist":"2B1","lyric":"토요일 밤 막차는 너무 싫어\n 뚜버기라 밤 열두 시 땡 치면\n 널 막차로 보내야만 하잖아\n 눈 딱 감고 오늘밤 가지 마라\n 말 차마 못해서 그만 남자는\n 외로움만 한 가득 품은 채"},{"url":"/artist/%EC%A0%84%EC%9A%A9%EC%88%98/Peters_Way_Of_%EC%A3%BC%EC%B2%AD%ED%94%84%EB%A1%9C%EC%A0%9D%ED%8A%B8/","subject":"Peter`s Way (Of 주청프로젝트)","artist":"전용수","lyric":"나 두려워서\n 주를 모른다 말했지\n 한 번 두 번도 세 번도\n 나는 두려웠어요\n 나는 두려워서\n 주를 모른다 말했지\n 한 번 두 번도 세 번도\n 너무 두려웠어요\n 닭이 울고 나는 "},{"url":"/artist/%EB%A9%94%EB%A6%AC%EA%B7%B8%EB%9D%BC%EC%9A%B4%EB%93%9C/%EC%9D%B8%EB%94%94%EC%96%B8_%EC%8D%B8%EB%A8%B8_Indian_Summer/","subject":"인디언 썸머 (Indian Summer)","artist":"메리그라운드","lyric":"Don’t kiss me \n 아무런 노력 없이 \n 너는 항상 열매를 가져갔지 \n 비 바람 \n 폭풍우를 견딜 때 \n 어디에도 없는 \n 너를 원망 안 했어 \n 이 계절이 지나면 \n 나"},{"url":"/artist/%ED%9E%88%EC%A6%88%EC%87%BC/%EB%A7%88%EB%9D%BC%EB%82%98%ED%83%80_%EC%BA%90%EB%A1%A4/","subject":"마라나타 캐롤","artist":"히즈쇼","lyric":"Intro)\n 기쁘다 구주 다시 오시네 \n 만백성 맞으라\n \n 간주)\n \n Verse)\n 이천년 전 추운 겨울날\n 베들레헴 작은 마굿간\n 아기 예수 우리를 구원하시려\n 이 땅에 오"},{"url":"/artist/5_Seconds_Of_Summer/Out_Of_My_Limit/","subject":"Out Of My Limit","artist":"5 Seconds Of Summer","lyric":"Back in high school we used to take it slow\n Red lipstick on and high heel stilettos\n Had a job down"},{"url":"/artist/5_Seconds_Of_Summer/Close_As_Strangers/","subject":"Close As Strangers","artist":"5 Seconds Of Summer","lyric":"Six weeks since I've been away\n And now you're sayin' everything has changed\n And I'm afraid that I "}]}