{"last":1,"data":[{"url":"/artist/Cairobi/Zoraide/","subject":"Zoraide","artist":"Cairobi","lyric":"I'll get it off my chest but\n Not jut like anyone else would\n Not jut like anyone else would\n \n I'll"},{"url":"/artist/Cairobi/Lupo/","subject":"Lupo","artist":"Cairobi","lyric":"That's the day I've been waiting for\n Driving slow around with you\n From the hill where the sun is l"},{"url":"/artist/Cairobi/Lupo/","subject":"Lupo","artist":"Cairobi","lyric":"That's the day I've been waiting for\n Driving slow around with you\n From the hill where the sun is l"}]}