{"data":[{"url":"/artist/Pink_Martini/Pata_Pata/","subject":"Pata Pata","artist":"Pink Martini","lyric":"Saguquka sathi bheka \n Nants’ iPata Pata \n Saguquka sathi bheka \n Nants’ iPata Pata \n Saguquka sathi"},{"url":"/artist/Pink_Martini/Fini_La_Musique/","subject":"Fini La Musique","artist":"Pink Martini","lyric":"Fini la musique la foule defile \n Parti le public que reste t’il \n La lumiere s’eteint \n et te voila"},{"url":"/artist/Pink_Martini/Blue_Moon/","subject":"Blue Moon","artist":"Pink Martini","lyric":"Once upon a time \n Before I took up smiling \n I hated the moonlight \n Shadows of the night \n That po"},{"url":"/artist/Pink_Martini/Askim_Bahard%C4%B1/","subject":"Askim Bahardı","artist":"Pink Martini","lyric":"Askim bahardi\n Umitler vardi\n Sen gittin diye\n GonlUm karardi\n Askim bahardi\n Umitler vardi\n Sen git"},{"url":"/artist/Pink_Martini/Souvenir/","subject":"Souvenir","artist":"Pink Martini","lyric":"Te souviens-tu des nuits \n sous les etoiles\n C'est mon precieux souvenir\n Nos coeurs brulent \n comme"},{"url":"/artist/Pink_Martini/Solidao/","subject":"Solidao","artist":"Pink Martini","lyric":"Solidao de quem tremeu\n A tentacao do ceu\n E desencanto que o ceu me deu\n Serei bem eu\n Sobre este v"},{"url":"/artist/Pink_Martini/Love_For_Sale/","subject":"Love For Sale","artist":"Pink Martini","lyric":"Love for sale \n Appetizing young love for sale \n Love that's fresh \n and still unspoiled \n Love that"},{"url":"/artist/Pink_Martini/The_Butterfly_Song/","subject":"The Butterfly Song","artist":"Pink Martini","lyric":"Butterfly \n Dance across the sky to me \n Come and spend some time with me \n I promise not to pin you"},{"url":"/artist/Pink_Martini/Joli_Garcon/","subject":"Joli Garcon","artist":"Pink Martini","lyric":"Combien de nuits sans sommeil \n Combien de jours sans soleil \n Les jours sans amour c’est fini \n Tu "}]}