{"data":[{"url":"/artist/%EB%9D%BC%EC%95%84%EC%89%AC/%EB%8F%84%EC%8B%9C_%EC%A5%90%EC%99%80_%EC%8B%9C%EA%B3%A8_%EC%A5%90/","subject":"도시 쥐와 시골 쥐","artist":"라아쉬","lyric":"가 보지 않은 곳을 가는 것\n 두려움이 생길지 몰라\n 보이지 않는 곳을 가는 것\n 무서움이 생길지 몰라\n \n 그래도 가 보자 그래도 가 보자\n 사람들이 많은 도시를 \n \n 그래도 "},{"url":"/artist/%EB%9D%BC%EC%95%84%EC%89%AC/%EA%B7%B8%EA%B1%B4_%EB%B0%94%EB%A1%9C_%EB%AC%B4%EC%A7%80%EA%B0%9C_Remix/","subject":"그건 바로 무지개 (Remix)","artist":"라아쉬","lyric":"빨 주 노 초 파 남 보\n 빨 주 노 초 파 남 보\n 일곱 빛깔 친구들이 함께 모였네\n 빨강친구 주황친구\n 노랑친구 초록친구\n 파랑친구 남색친구 보라친구\n 아름다운 색깔들이 모이면"},{"url":"/artist/%EB%9D%BC%EC%95%84%EC%89%AC/%EA%B7%B8%EA%B1%B4_%EB%B0%94%EB%A1%9C_%EB%AC%B4%EC%A7%80%EA%B0%9C/","subject":"그건 바로 무지개","artist":"라아쉬","lyric":"빨 주 노 초 파 남 보\n 빨 주 노 초 파 남 보\n 일곱 빛깔 친구들이 함께 모였네\n 빨강친구 주황친구\n 노랑친구 초록친구\n 파랑친구 남색친구 보라친구\n 아름다운 색깔들이 모이면"},{"url":"/artist/%EB%9D%BC%EC%95%84%EC%89%AC/%EC%A0%A4%EB%A6%AC%EA%B0%80_%EC%9E%85_%EC%95%88%EC%97%90_%EC%8F%99/","subject":"젤리가 입 안에 쏙!","artist":"라아쉬","lyric":"젤리가 입 안에 쏘옥\n 젤리가 입 안에 쏘옥 \n 젤리가 입 안에 쏙 \n 젤리가 입 안에 쏙\n 상큼 시큼 달콤 \n 상큼 시큼 달콤 \n 한번 먹고 두 번 먹고 세 번 먹고\n 한번 먹고"}]}