{"data":[{"url":"/artist/%ED%82%A4%EB%94%94%EB%B9%84_KittiB/%EC%B4%88%EC%86%8D_5cm_Inst/","subject":"초속 5cm (Inst.)","artist":"키디비 (KittiB)","lyric":"시간은 tic toc 잘 흘러가지 \n 어느새 너도 가벼운 차림 \n 각자의 겨울은 \n 지난밤의 꾼 꿈처럼 \n 희미한 기억이 되어가지 \n 너와 걷고 있는 분홍빛 길 \n 무심한 두 팔의"},{"url":"/artist/%ED%82%A4%EB%94%94%EB%B9%84_KittiB/%EC%B4%88%EC%86%8D_5cm/","subject":"초속 5cm","artist":"키디비 (KittiB)","lyric":"시간은 tic toc 잘 흘러가지 \n 어느새 너도 가벼운 차림 \n 각자의 겨울은 \n 지난밤의 꾼 꿈처럼 \n 희미한 기억이 되어가지 \n 너와 걷고 있는 분홍빛 길 \n 무심한 두 팔의"},{"url":"/artist/%ED%82%A4%EB%94%94%EB%B9%84_KittiB/%EC%9D%8C%EC%84%B1%EB%A9%94%EB%AA%A8_Feat_QM/","subject":"음성메모 (Feat. QM)","artist":"키디비 (KittiB)","lyric":"요즘 내 폰 음성메모엔 \n 음기 가득한 가사와 노래 \n 그 어느 때보다 더 짙게 베인 상처 \n 티비를 틀면 으슬으슬해 \n 성공이란 코트를 걸쳐 입고 \n 먼저 저 앞을 걷는 \n 이들"},{"url":"/artist/%ED%82%A4%EB%94%94%EB%B9%84_KittiB/Nobodys_Perfect/","subject":"Nobody`s Perfect","artist":"키디비 (KittiB)","lyric":"외출을 할 때 거울 앞의 난\n 미간에 주름 한 번은 잡고\n 관리 태만 빨간 불이 들어오네 자꾸\n 어떤 재난 영화보다 무서운 노화를\n 막을 수는 없네\n 점점 짙어지는 메이크업과의 사"}]}