{"last":2,"data":[{"url":"/artist/Merle_Haggard/Our_Paths_May_Never_Cross_Live/","subject":"Our Paths May Never Cross (Live)","artist":"Merle Haggard","lyric":"Lady I know your out there somewhere\n Like me your feeling lost\n Maybe right now we both need each o"},{"url":"/artist/Merle_Haggard/Always_Late_With_Your_Kisses_Live/","subject":"Always Late With Your Kisses (Live)","artist":"Merle Haggard","lyric":"Always late with your kisses\n Won't you come to my arms\n Sweet darling and stay\n Always late with yo"},{"url":"/artist/Merle_Haggard/I_Think_Ill_Just_Stay_Here__Drink_Live/","subject":"I Think I`ll Just Stay Here & Drink (Live)","artist":"Merle Haggard","lyric":"Could be holding you tonight\n Could quit doing wrong, start doin' right\n You don't care about what I"},{"url":"/artist/Merle_Haggard/Brain_Cloudy_Blues_Live/","subject":"Brain Cloudy Blues (Live)","artist":"Merle Haggard","lyric":"My brain is cloudy my soul is upside down\n Lord my brain is cloudy my soul is upside down\n When I ge"},{"url":"/artist/Merle_Haggard/Misery_And_Gin_Live/","subject":"Misery And Gin (Live)","artist":"Merle Haggard","lyric":"Memories and drinks don't mix too well\n And jukebox records don't play those wedding bells\n Looking "},{"url":"/artist/Merle_Haggard/Santa_Claus_Is_Coming_To_Town/","subject":"Santa Claus Is Coming To Town","artist":"Merle Haggard","lyric":"You better watch out you better not cry\n You better not pout I'm tellin' you why\n Santa Claus is com"},{"url":"/artist/Merle_Haggard/Goin_Home_For_Christmas_Album_Ver/","subject":"Goin` Home For Christmas (Album Ver.)","artist":"Merle Haggard","lyric":"My family called me on the phone and said\n Grandpa, would you come home\n We'd love to have you here "}]}