{"data":[{"url":"/artist/%EB%A5%BCLEL/%EB%81%9D%EA%B3%BC_%EB%81%9D/","subject":"끝과 끝","artist":"를(LEL)","lyric":"끝난걸까 생각될 때가 있지\n 에스컬레이터는 여전히\n 반대로 가고 있는데\n 제자리야\n 세상 가득했던\n 아름다운 척 했던 모순들이\n 오랫동안 원치 않는\n 상처를 주었지만 이제는\n 끝과"},{"url":"/artist/%EB%A5%BCLEL/%EC%84%9C%EB%A1%9C%EA%B0%80_%EC%84%9C%EB%A1%9C%EB%A5%BC/","subject":"서로가 서로를","artist":"를(LEL)","lyric":"꽉찬 서울 벅찬 도로 \n 성난 듯이 달리는 차들 \n 울부짖는 네온사인 \n 각자의 목표 각자의 꿈들 \n 각자의 희망 각자의 슬픔 \n 서로가 서로를 서로가 서로를\n 서로가 서로를 감싸"},{"url":"/artist/%EB%A5%BCLEL/%ED%97%88%EB%A6%AC%EB%A5%BC_%EA%B0%90%EC%95%84/","subject":"허리를 감아","artist":"를(LEL)","lyric":"내 등 뒤에 예쁜 너를 태우고\n 예쁜 너를 태우고\n 가장 빠르게 달릴 거야\n 망설이지 말고 어서 허리를 감아\n 바람 속에 상념들이 날아가도록\n 빠르게 지나간 풍경이 무섭다면\n 내 "},{"url":"/artist/%EB%A5%BCLEL/%EA%B2%80%EB%B6%89%EC%9D%80_%EA%BD%83/","subject":"검붉은 꽃","artist":"를(LEL)","lyric":"검붉은 꽃이 된 너는\n 꽃가루 속에 피어나\n 스며드는 널 녹아 내린 날\n 아프지 않도록 끝내줄 수는 없니\n 내 맘이 모래가 될 수 있다면\n 편해 질 텐데\n 여전히 태연한 표정을 짓"},{"url":"/artist/%EB%A5%BCLEL/%EC%B9%A8%EB%AC%B5%EC%9D%98_%ED%95%A8%EC%84%B1/","subject":"침묵의 함성","artist":"를(LEL)","lyric":"정처 없이 한참을 떠돌다 \n 우연히 닿은 그 곳 \n 진달래가 끝도 없이 펼쳐져 \n 한참을 이어갔지\n 내 눈앞에 다람쥐 한 마리 \n 가까이 다가 가면 \n 나무위로 달아나 버리고 \n "},{"url":"/artist/%EB%A5%BCLEL/%EB%AA%A8%EB%93%A0_%EC%83%89%EA%B9%94%EC%9D%B4_%EB%B9%9B%EC%9D%B4_%EB%82%98%EA%B2%8C/","subject":"모든 색깔이 빛이 나게","artist":"를(LEL)","lyric":"내 맘속에 흉터 붓으로 쓸어봐도 \n 가슴 깊게 박힌 억압들 남아있어 \n 상처투성이가 된 내 맘 \n 블러드 번져도 \n 붉은 색깔 속에 유토피아 \n 찾게 되는걸 \n 차가운 땅 위에 차"},{"url":"/artist/%EB%A5%BCLEL/%EB%AF%B8%EC%B9%9C_%EA%B3%BC%ED%95%99%EC%9E%90%EC%9D%98_%EC%82%AC%EB%9E%91/","subject":"미친 과학자의 사랑","artist":"를(LEL)","lyric":"뭐해\n 타임머신 만들고 있어\n 병신 지랄하고 자빠졌네\n 무슨 얼어 죽을 타임머신이야\n 아지랑이 모습이 점점 흩어져간다\n 설레었던 마음이 사라져 버렸니\n 어떻게 어떻게 그러니\n 아직"},{"url":"/artist/%EB%A5%BCLEL/%EB%8B%AE%EC%9D%80_%EB%A7%88%EC%9D%8C/","subject":"닮은 마음","artist":"를(LEL)","lyric":"같은 색을 찾을 순 없었지\n 컴퓨터 속에만 있을 뿐\n 하지만 닮은 색깔은 있었어\n 그게 바로 너와 나인 걸\n 사실 조금 놀랐어 섬세한\n 표정 속에 단어를 고르는 너\n 하지만 난 어"},{"url":"/artist/%EB%A5%BCLEL/IF/","subject":"IF","artist":"를(LEL)","lyric":"참 평범하던 모습도\n 아름답게 간직되고\n 내 마음은 그대로 가득해\n 소중한 기억들이\n 아픔에 부서진데도\n 담담히 주워서\n 꼭 안고 있을꺼야\n 혹시라도 그대 사라지면\n 운명을 만들어"},{"url":"/artist/%EB%A5%BCLEL/%ED%91%B8%EB%A5%B8_%EC%95%88%EA%B0%9C_Vocal_By_LEL/","subject":"푸른 안개 (Vocal By LEL)","artist":"를(LEL)","lyric":"세상에는 여러 가지 \n 푸른색이 있지 \n 우리가 알지 못하는 곳에도\n 어쩔 때는 짙은 안개로 \n 뒤덮여있어 \n 잡힐 듯 말듯 답답할 때도 있지\n 아름다운 푸른색이 있다면 \n 멍과 "}]}