{"data":[{"url":"/artist/Li_bertus/Rainbows_End_Feat_Calvin_Of_Twilight/","subject":"Rainbow`s End (Feat. Calvin Of Twilight)","artist":"Li_bertus","lyric":"Under the rain \n the Blindness falls \n All I can do \n Is wandering on a street road \n With no one he"},{"url":"/artist/Li_bertus/Snow_Was_Falling_Feat_%EC%A0%95%EC%88%98%EC%A0%95/","subject":"Snow Was Falling (Feat. 정수정)","artist":"Li_bertus","lyric":"Can't believe\n The dark sky looks bright\n with stars on\n and surrounding air feels\n It feels like wa"}]}