{"data":[{"url":"/artist/%EB%AA%A8%EB%B8%8C%EB%8B%9D_MOVNING/TURNING_LIGHT/","subject":"TURNING LIGHT","artist":"모브닝 (MOVNING)","lyric":"그래\n 꼭 털어놓지 않아도 돼\n 너의 눈에 먹구름이 되어버린\n 아이라인 Shadow\n 너의 하루를 다 말해주고 있어\n no no no yeah yeah \n yeah eh yeah "},{"url":"/artist/%EB%AA%A8%EB%B8%8C%EB%8B%9D_MOVNING/Touch_me_Lady/","subject":"Touch me Lady","artist":"모브닝 (MOVNING)","lyric":"보일듯 말듯 정답은 \n 늘 쉽게 보이질 않죠 \n 닿을듯 말듯 \n 그대와 나의 거리는 \n 딱 이만큼이라는게 \n 딱딱하게 굳어있는 이 \n 어색한 방안이 \n 참 싫어요 \n 달빛보단 햇빛"},{"url":"/artist/%EB%AA%A8%EB%B8%8C%EB%8B%9D_MOVNING/You_are_a_Rainbow/","subject":"You are a Rainbow","artist":"모브닝 (MOVNING)","lyric":"말하지 않아도\n 다 알것 같아요\n 당신의 눈가에\n 쏟아지는 햇살이\n 마냥 반갑지만은\n 않았을 거에요\n 그냥 아침이 오지\n 않길 바랬겠죠\n 언제나 기대보다\n 걱정이 앞서는 하루에\n "},{"url":"/artist/%EB%AA%A8%EB%B8%8C%EB%8B%9D_MOVNING/Silly_Man/","subject":"Silly Man","artist":"모브닝 (MOVNING)","lyric":"Call me silly man \n 시작은 언제나 \n 가슴이 뛰는 일이야 \n 작은 미련이 \n 다시 커지는 길이야 \n 알어 잘알어 바늘구멍은 \n 너무나도 작은걸 \n 뭔가 잘못되가는 "}]}