{"data":[{"url":"/artist/New_Grass_Revival/White_Freight_Liner_Blues_Live/","subject":"White Freight Liner Blues (Live)","artist":"New Grass Revival","lyric":"I'm going out on the highway\n And listen to them big trucks wind\n I'm going out on the highway\n And "},{"url":"/artist/New_Grass_Revival/Skippin_In_The_Mississippi_Dew_Live/","subject":"Skippin` In The Mississippi Dew (Live)","artist":"New Grass Revival","lyric":"Well I dream of a girl and a steering wheel steamboat\n A pilothouse stove and engine room brass\n Han"}]}