{"last":1,"data":[{"url":"/artist/%ED%81%B4%EB%9D%BC%EC%9A%B0%EC%A6%88_%EB%B8%94%EB%A1%9D/%EB%91%A5%EA%B8%80%EA%B2%8C_%EA%B5%B4%EB%9F%AC%EA%B0%80%EB%8A%94_%EB%84%A4%EB%AA%A8%EB%82%9C_%EB%82%98/","subject":"둥글게 굴러가는 네모난 나","artist":"클라우즈 블록","lyric":"시간처럼 둥글게 굴러갔네\n 파도처럼 둥글게 밀려갔네\n 내 맘대로 혹은 내 맘과 다르게\n 둥글게 어쩌면 좀 미련하게\n 모난 상처를 그대로 받다가도\n 못난 이빨을 보이다 부러진다\n 도"},{"url":"/artist/%ED%81%B4%EB%9D%BC%EC%9A%B0%EC%A6%88_%EB%B8%94%EB%A1%9D/%EB%B0%A4_%EB%84%88/","subject":"밤, 너","artist":"클라우즈 블록","lyric":"네가 문을 열었니 비가 오는 창가를\n 너의 꿈이 모두 모여있을 비의 노래\n 나를 보듬어주렴 상처뿐인 입술로\n 누구의 이해도 바라지 않은\n 비의 소멸처럼\n 창문에 깨져버린 살굿빛 가"},{"url":"/artist/%ED%81%B4%EB%9D%BC%EC%9A%B0%EC%A6%88_%EB%B8%94%EB%A1%9D/%ED%99%98%ED%92%8D%EA%B8%B0%EB%A5%BC_%EC%BC%B0%EC%96%B4%EC%9A%94/","subject":"환풍기를 켰어요","artist":"클라우즈 블록","lyric":"환풍기를 켰어요 \n 이제 그대가 쉽게 \n 나갈 수 있어요\n 그대만의 이별에서 \n 나도 숨을 쉴 수 있게\n 그대에게는 지나간 일\n 나에겐 아직 머물고 있는 \n 어제와 그때\n 둘 중 "},{"url":"/artist/%ED%81%B4%EB%9D%BC%EC%9A%B0%EC%A6%88_%EB%B8%94%EB%A1%9D/Window/","subject":"Window","artist":"클라우즈 블록","lyric":"Here I am tracing your name \n on my Foggy window\n Here I pray someday you'll be \n tracing the letter"}]}