{"last":1,"data":[{"url":"/artist/Ohishi_Masayoshi/%E5%90%9B%E3%81%98%E3%82%83%E3%81%AA%E3%81%8D%E3%82%83%E3%83%80%E3%83%A1%E3%81%BF%E3%81%9F%E3%81%84___Kimijyanakya_Damemitai_%EB%84%A4%EA%B0%80_%EC%95%84%EB%8B%88%EB%A9%B4_%EC%95%88%EB%90%98%EB%8A%94_%EA%B2%83_%EA%B0%99%EC%95%84/","subject":"君じゃなきゃダメみたい / Kimijyanakya Damemitai (네가 아니면 안되는 것 같아)","artist":"Ohishi Masayoshi","lyric":"아노코가 키노우 난카 스고쿠 야사시쿠테\n Ano ko ga kinou nanka sugoku yasashikute\n \n (키미쟈나캬 다메미타이)\n (Kimi ja nakya dam"},{"url":"/artist/Ohishi_Masayoshi/%E3%82%88%E3%81%86%E3%81%93%E3%81%9D%E3%82%B8%E3%83%A3%E3%83%91%E3%83%AA%E3%83%91-%E3%82%AF%E3%81%B8___Youkoso_Japari_Park_E_%EC%96%B4%EC%84%9C%EC%98%A4%EC%84%B8%EC%9A%94_Japan_Park%EC%97%90/","subject":"ようこそジャパリパ-クへ / Youkoso Japari Park E (어서오세요 Japan Park에)","artist":"Ohishi Masayoshi","lyric":"웰컴투 요-코소 자파리파크!\n 쿄오모 돗탄밧탄 오오사와기\n 우-! 가오-!\n 다카라카니 와라이와라에바 후레은즈 (후레은즈)\n 게은카시떼 슷챠카멧챠카 시테모 나카요시 (후후후)\n 케"}]}