{"last":1,"data":[{"url":"/artist/Homme_%EC%B0%BD%EB%AF%BC_%EC%9D%B4%ED%98%84/%EC%96%B4%EB%94%94%EC%AF%A4_%EC%99%94%EB%8B%88/","subject":"어디쯤 왔니","artist":"Homme (창민, 이현)","lyric":"어디서 뭐하니\n 혼자 밥을 먹다가\n 문득 생각나서\n 괜시리 안부를 물어\n 아직도 멀었니\n 혼자 영활 보다가\n 텅 빈 옆자리가\n 유난히 허전해 보여\n 어디쯤 왔니 널 기다리잖아\n 오"},{"url":"/artist/Homme_%EC%B0%BD%EB%AF%BC_%EC%9D%B4%ED%98%84/%EB%84%88%EB%A7%8C%EC%9D%84_%EB%8A%90%EB%81%BC%EB%A9%B0/","subject":"너만을 느끼며","artist":"Homme (창민, 이현)","lyric":"네가 나이기를 바랐던 것만큼 \n 많은 것을 원하지는 않아 \n 알 수 없는 이 아쉬움들은 \n 그리움의 마음일 뿐 \n 오 짧았던 우리의 시간은 \n 오랜 아픔으로 남겠지만 \n 모든 것이"},{"url":"/artist/Homme_%EC%B0%BD%EB%AF%BC_%EC%9D%B4%ED%98%84/%EB%82%B4%EA%B2%90_%EC%A0%84%EB%B6%80%EB%8B%88%EA%B9%8C/","subject":"내겐 전부니까","artist":"Homme (창민, 이현)","lyric":"늘 머리를 묶고\n 큰 셔츠를 입는\n 내 사랑 내 사랑\n 넌 내 전부니까\n 늘 투정부리고\n 툭 하면 화내도\n 내 사랑 내 사랑\n 넌 내 전부니까\n 사랑해 난 널 사랑해\n 너 없이 살"}]}