{"last":1,"data":[{"url":"/artist/%EA%B9%80%EC%9C%A4%ED%9D%AC/Good-bye_Sadness_Hello_Happiness/","subject":"Good-bye Sadness, Hello Happiness","artist":"김윤희","lyric":"And now It's Over\n 사랑은 끝났어\n 우리 추억은 여기까진가 봐\n 영원하라 했던 말\n I so love you\n 이젠 시간 속으로 흩어져가\n 함께 했었던 세상의 모든 "},{"url":"/artist/%EA%B9%80%EC%9C%A4%ED%9D%AC/%EC%96%B4%EC%A0%9C%EC%B2%98%EB%9F%BC/","subject":"어제처럼","artist":"김윤희","lyric":"Trust the warmth inside woo\n Please don't tell me why woo\n 내게 이런 말하기가\n 쉽진 않았을 거야\n 생각해봤어 얼마나 어려웠을지\n 다"},{"url":"/artist/%EA%B9%80%EC%9C%A4%ED%9D%AC/Officially_Missing_You/","subject":"Officially Missing You","artist":"김윤희","lyric":"All I hear is raindrops falling\n on the rooftop\n Ooh baby\n tell me why'd you have to go\n 'Cause this"}]}