{"last":1,"data":[{"url":"/artist/%ED%8F%B4_%EC%97%90%EC%8A%A4%EC%B9%B4_PAUL_ESKHA/ROUGH_TOUGH_TUP/","subject":"ROUGH TOUGH TUP","artist":"폴 에스카 (PAUL ESKHA)","lyric":"넌 visual top인 girl\n 난 너와 있기도\n 불편해질 것 같아\n because I’m cheer up uh\n 내 말은 skinny fit을\n 입은 이 it's me\n 텅 "},{"url":"/artist/%ED%8F%B4_%EC%97%90%EC%8A%A4%EC%B9%B4_PAUL_ESKHA/%EB%8B%A4%EC%8B%9C_%ED%83%9C%EC%96%B4%EB%82%98_Feat_Gem_I_East_Q/","subject":"다시 태어나 (Feat. Gem I, East Q)","artist":"폴 에스카 (PAUL ESKHA)","lyric":"다시 태어나 다다다 다시 태어나\n 넌 이번 생에는 글렀으니까\n 다시 태어나\n 모두다 같이 배워놔\n 처음부터 다시 배워 넌\n 이미 한계에 다다른 넌 다시 태어나\n 다시 태어나 다다다"},{"url":"/artist/%ED%8F%B4_%EC%97%90%EC%8A%A4%EC%B9%B4_PAUL_ESKHA/Dawn/","subject":"Dawn","artist":"폴 에스카 (PAUL ESKHA)","lyric":"저 차가운 밤을\n 깨운 그 다음\n 묶여 있던 내 가지 들에 닿게 펴\n 내일의 자주색 하늘\n I am in dawn\n 숨을 내 쉬듯 \n La Li Lalala baby\n 눈뜬 동공 "},{"url":"/artist/%ED%8F%B4_%EC%97%90%EC%8A%A4%EC%B9%B4_PAUL_ESKHA/Be_Art/","subject":"Be Art","artist":"폴 에스카 (PAUL ESKHA)","lyric":"Scenes top thrill uh\n 내가 나타났으니까\n 구름에 닿기 전에\n 자만은 자리로 차분히 돌아가\n 약간 어지러운 듯\n 이 태풍에 나를 더\n 주시 해야 하는 게\n 모든 이"}]}