{"data":[{"url":"/artist/%EB%B0%94%EC%84%B8%EB%A6%B0_VASSLINE/Tracing_The_Untraceable_Memoir_Ver/","subject":"Tracing The Untraceable (Memoir Ver.)","artist":"바세린 (VASSLINE)","lyric":"Since the beginning of the time\n walked through the white darkness\n I am the law this\n must be perfe"},{"url":"/artist/%EB%B0%94%EC%84%B8%EB%A6%B0_VASSLINE/Flowers_In_The_Sand_Memoir_Ver_By_LoveXstereo/","subject":"Flowers In The Sand (Memoir Ver.) (By LoveXstereo)","artist":"바세린 (VASSLINE)","lyric":"Walked through \n this state of completion \n I feel the end is near \n I couldn’t tell anyone \n anyone"},{"url":"/artist/%EB%B0%94%EC%84%B8%EB%A6%B0_VASSLINE/Memories_Of_One_Memoir_Ver/","subject":"Memories Of One (Memoir Ver.)","artist":"바세린 (VASSLINE)","lyric":"These are the memories\n that will never fade\n No matter what we face\n some things never change\n I wi"},{"url":"/artist/%EB%B0%94%EC%84%B8%EB%A6%B0_VASSLINE/Fear_Coming_Memoir_Ver/","subject":"Fear Coming (Memoir Ver.)","artist":"바세린 (VASSLINE)","lyric":"Words can't tell pain \n and tragedy \n The pain cut from me \n is the pain you feel \n pain you feel \n "},{"url":"/artist/%EB%B0%94%EC%84%B8%EB%A6%B0_VASSLINE/The_Protester_Live_Ver/","subject":"The Protester (Live Ver.)","artist":"바세린 (VASSLINE)","lyric":"Preparing the end of darkness\n the red frozen sun now rises\n Wishing for one ordinary day\n and it wa"},{"url":"/artist/%EB%B0%94%EC%84%B8%EB%A6%B0_VASSLINE/An_Ode_To_My_Friend_Memoir_Ver/","subject":"An Ode To My Friend (Memoir Ver.)","artist":"바세린 (VASSLINE)","lyric":"Sitting there \n just thinking things over \n It's everything that you do \n In your head so full of sh"},{"url":"/artist/%EB%B0%94%EC%84%B8%EB%A6%B0_VASSLINE/Eternal_Recurrence_Memoir_Ver/","subject":"Eternal Recurrence (Memoir Ver.)","artist":"바세린 (VASSLINE)","lyric":"Sometimes I ask myself\n If life was a never-ending cycle\n which repeats itself\n like a Ferris Wheel\n"},{"url":"/artist/%EB%B0%94%EC%84%B8%EB%A6%B0_VASSLINE/Against_The_Tide_Memoir_Ver/","subject":"Against The Tide (Memoir Ver.)","artist":"바세린 (VASSLINE)","lyric":"Against the tide of all \n negativity and anxiety\n we rise and stand here \n to keep the pride\n Yes th"},{"url":"/artist/%EB%B0%94%EC%84%B8%EB%A6%B0_VASSLINE/Red_Raven_Conspiracy_Memoir_Ver/","subject":"Red Raven Conspiracy (Memoir Ver.)","artist":"바세린 (VASSLINE)","lyric":"My dearest friend \n you finally came crawling back\n After all these years \n in pain and vanity\n For "},{"url":"/artist/%EB%B0%94%EC%84%B8%EB%A6%B0_VASSLINE/24HRS_Memoir_Ver/","subject":"24HRS (Memoir Ver.)","artist":"바세린 (VASSLINE)","lyric":"The 24 hours inside my hand\n God damn it \n this day must be the longest day\n All of a sudden \n every"}]}